[
  {
    "movieCd": "20250523",
    "movieNm": "결혼해줄래?",
    "openDt": "2026-03-04",
    "genreNm": "",
    "nationAlt": "한국",
    "director": "장완복",
    "isReRelease": false,
    "overview": ""
  },
  {
    "movieCd": "20256787",
    "movieNm": "노 어더 랜드",
    "openDt": "2026-03-04",
    "genreNm": "다큐멘터리",
    "nationAlt": "팔레스타인,노르웨이",
    "director": "Basel Adra,Hamdan Ballal,Yuval Abraham,Rachel Szor",
    "isReRelease": false,
    "overview": "바젤은 팔레스타인 서안지구 웨스트 뱅크의 마사페르 야타 출신의 젊은 팔레스타인 활동가다. 그는 어릴 때부터 이스라엘 군의 강제적인 마을 철거에 저항하며 마을의 현실을 기록해 왔다. 그러던 중 팔레스타인을 돕는 기사를 쓰기 위해 온 젊은 이스라엘 저널리스트 유발과 친해지고, 둘 사이에는 예기치 않은 유대감이 생긴다. 그러나 불과 30분 거리에 살지만 완전히 다른 세계에서 사는 둘 사이에는 건널 수 없는 차이가 존재한다.",
    "posterUrl": "https://image.tmdb.org/t/p/w500/dU9thX37Bd8Um30UpjCVO0VqJps.jpg"
  },
  {
    "movieCd": "20250413",
    "movieNm": "다이 마이 러브",
    "openDt": "2026-03-04",
    "genreNm": "드라마",
    "nationAlt": "미국",
    "director": "린 램지",
    "isReRelease": false,
    "overview": "미친 듯이 사랑했던 그레이스와 잭슨에게 아기가 생긴다. 불처럼 타오르던 두 사람의 사랑은 서서히 꺼져가고 섹스마저 말라붙는다. 외로움이 깊어진 그레이스는 작가로서의 글쓰기도 불가능해지고, 점점 자신을 파괴하기 시작한다. 그 모든 붕괴를 곁에서 지켜보는 잭슨은 이 사랑을 다시 되돌릴 수 없을지도 모른다는 두려움에 사로잡힌다.",
    "posterUrl": "https://image.tmdb.org/t/p/w500/p2HjLmgZ7PNjlkkKPx5va17EKkX.jpg"
  },
  {
    "movieCd": "20241501",
    "movieNm": "매드 댄스 오피스",
    "openDt": "2026-03-04",
    "genreNm": "코미디,음악",
    "nationAlt": "한국",
    "director": "조현진",
    "isReRelease": false,
    "overview": "24시간 빈틈없이 살아온 구청의 갓생 과장 국희. 승진은 코앞이고, 딸의 취업까지! 모든 것이 그녀의 계획대로 완벽하게 진행될 줄 알았다. 그런데 완벽했던 스텝이 꼬여버리기 시작한다! 도둑맞은 승진, 연락 두절된 딸, 그리고 텅 빈 마음... 엉망진창이 된 인생 박자를 수습하기 위해 찾아간 곳은 플라멩코 연습실? 완벽하지 않아도 괜찮은, 인생 리듬 되찾기 프로젝트!",
    "posterUrl": "https://image.tmdb.org/t/p/w500/5tUNj2UXAwgZ9tYYPlaDzn4DjuU.jpg"
  },
  {
    "movieCd": "20258444",
    "movieNm": "브라이드!",
    "openDt": "2026-03-04",
    "genreNm": "SF,공포,판타지",
    "nationAlt": "미국",
    "director": "매기 질렌할",
    "isReRelease": false,
    "overview": "1930년대 미국, 죽음에서 깨어난 브라이드와 그녀를 사랑하게 된 프랑켄슈타인. 어느 날, 끔찍한 사건을 저지르고 위험천만한 도주를 시작한다. 세상의 모든 규범을 깨부순 브라이드와 프랑켄슈타인의 파격적인 행보는 미국 전역을 뒤흔들고 그들의 운명은 걷잡을 수 없는 방향으로 치닫는데…",
    "posterUrl": "https://image.tmdb.org/t/p/w500/ftIYdV8IEE4n8odMv7FLam9VDVy.jpg"
  },
  {
    "movieCd": "20250875",
    "movieNm": "우리는 매일매일",
    "openDt": "2026-03-04",
    "genreNm": "로맨스,드라마",
    "nationAlt": "한국",
    "director": "김민재",
    "isReRelease": false,
    "overview": "중학교 졸업이 얼마 남지 않은 날, ‘여울’은 소꿉친구 ‘호수’에게 갑작스러운 고백공격을 받았다! 친구 이상으로 생각할 수 없기에, 단칼에 거절했는데… 그녀석을 고등학교에서 다시 만날 줄이야! ‘여울’은 ‘호수’를 볼 때마다, 마음 한구석이 불편하다. 다시는 예전처럼 돌아갈 수 없게 되었다는 것도, 짜증이 난다. 그러던 중, ‘여울’은 홧김에 농구부 선배에게 고백을 저질러버리고 그들의 첫사랑은 점점 더 혼란에 빠지고 마는데…",
    "posterUrl": "https://image.tmdb.org/t/p/w500/AqHIHvAxs5dKG1rW19rqevEdBSB.jpg"
  },
  {
    "movieCd": "20249843",
    "movieNm": "우리에게는 아직 내일이 있다",
    "openDt": "2026-03-04",
    "genreNm": "드라마,코미디,역사",
    "nationAlt": "이탈리아",
    "director": "Paola Cortellesi",
    "isReRelease": false,
    "overview": "나라의 운명이 걸린 국민투표로 소란한 1946년 이탈리아. 과거에 없던 투표권이 생겼지만 여전히 발언권은 없는 산투치 가문의 며느리 델리아는 오늘도 딸 마르첼라의 결혼식 준비에 한창이다. 그러던 어느 날 델리아 앞으로 의문의 편지가 도착하고 델리아는 난생처음 비밀스러운 계획을 세우는데…",
    "posterUrl": "https://image.tmdb.org/t/p/w500/hWFpY2ZxHQdtmPBipT7Abpu5rvQ.jpg"
  },
  {
    "movieCd": "20258709",
    "movieNm": "좀비 랜드 사가: 유메긴가 파라다이스",
    "openDt": "2026-03-04",
    "genreNm": "애니메이션,코미디,음악,액션",
    "nationAlt": "일본",
    "director": "Takafumi Ishida,Takeru Sato",
    "isReRelease": false,
    "overview": "좀비 아이돌 프랑슈슈의 만국박람회 무대로 인류를 위협하는 정체불명의 존재가 다가오고, 전무후무한 갤럭시 페스티벌이 시작된다.",
    "posterUrl": "https://image.tmdb.org/t/p/w500/fm2q4fIDnxhO9KNKVBwJ8TCjD8K.jpg"
  },
  {
    "movieCd": "20250087",
    "movieNm": "차임",
    "openDt": "2026-03-04",
    "genreNm": "공포,스릴러",
    "nationAlt": "일본",
    "director": "구로사와 기요시",
    "isReRelease": false,
    "overview": "요리 교실 강사로 일하고 있는 마츠오카. 어느 날 한 수강생이 차임벨 소리가 자신을 조종한다는 이상한 말을 하고는 충격적인 행동을 한다. 그의 광기는 점점 마츠오카에게 전염되기 시작하는데… 모든 것은 차임벨 소리에서 시작되었다.",
    "posterUrl": "https://image.tmdb.org/t/p/w500/eclmUxGOu3ui9PEl8Ri25YlZBpw.jpg"
  },
  {
    "movieCd": "20261694",
    "movieNm": "투어스 브이알 콘서트 : 러쉬로드",
    "openDt": "2026-03-04",
    "genreNm": "",
    "nationAlt": "한국",
    "director": "김지애",
    "isReRelease": false,
    "overview": ""
  },
  {
    "movieCd": "20261679",
    "movieNm": "페루지노. 영원한 르네상스",
    "openDt": "2026-03-04",
    "genreNm": "다큐멘터리",
    "nationAlt": "이탈리아",
    "director": "Giovanni Piscaglia",
    "isReRelease": false,
    "overview": "A tribute to an artist who inspired great painters in a decisive way, by creating works of immortal beauty. His art straddles two worlds: on the one hand the architecture of Piero della Francesca and on the other the devotional painting. Perugino achieved in painting a perfect balance between human being and nature, reality and ideal. He invented compositions and iconographies that set the school, spread a new ideal of female beauty through his Madonnas, and conceived extraordinary fresco cycles as in the Collegio del Cambio in Perugia. A journey through Italy to discover his great masterpieces, from the frescoes of the Sistine Chapel to the two rooms entirely dedicated to him in the National Gallery of Umbria.",
    "posterUrl": "https://image.tmdb.org/t/p/w500/jbYpoZXtdC4aGOxfJ8bd3P1xOBg.jpg"
  },
  {
    "movieCd": "20256283",
    "movieNm": "호퍼스",
    "openDt": "2026-03-04",
    "genreNm": "애니메이션,가족,SF,코미디,모험",
    "nationAlt": "미국",
    "director": "다니엘 총",
    "isReRelease": false,
    "overview": "오랜 연구 끝에 개발한 ‘호핑’ 기술로 동물 세계에 가까이 갈 수 있음을 알게 된 주인공 ‘메이블’은 마치 ‘아바타’ 같다며 신기해하고, 직접 로봇 비버가 되어 동물들의 세계에 잠입한다. 그들의 말을 알아듣게 된 ‘메이블’은 진짜 동물이 된 것처럼 동물 세상을 경험하는 가운데, 연못에 있던 다른 비버에게 달려드는 곰을 막아서지만 그들에겐 그들만의 질서와 법칙이 있다는 사실을 알게 된다. ‘호핑‘ 기술을 개발한 박사는 이 기술을 자연계 질서를 어지럽히는 데 쓰면 안 된다고 경고하지만, ‘메이블’은 통신을 끊어버려 이후 예측불가의 모험이 펼쳐질 것을 예고한다.",
    "posterUrl": "https://image.tmdb.org/t/p/w500/vJu9THzQ26Q5sWOVnhOkuRH5M1P.jpg"
  },
  {
    "movieCd": "20261052",
    "movieNm": "더치스: 복수의 화신",
    "openDt": "2026-03-05",
    "genreNm": "액션,범죄,스릴러",
    "nationAlt": "영국",
    "director": "닐 마샬",
    "isReRelease": false,
    "overview": "소매치기 그녀, 다이아몬드 밀매자와 사랑에 빠지고 암흑가로 입성한다. 그러나 배신으로 눈 앞에서 그를 잃고 죽음의 문턱에서 돌아온 그녀. 독기가 바짝 올랐다. 오직 피의 복수다. 독하고 잔혹한 응징이 시작되는데…",
    "posterUrl": "https://image.tmdb.org/t/p/w500/2B5UoehQijzwuV25MUZNIaLqMeP.jpg"
  },
  {
    "movieCd": "20261871",
    "movieNm": "허리 업 투모로우",
    "openDt": "2026-03-05",
    "genreNm": "음악,스릴러,드라마",
    "nationAlt": "미국",
    "director": "트레이 에드워드 슐츠",
    "isReRelease": false,
    "overview": "전설적인 가수, 아벨은 이별로 무너진다. 그런 아벨 앞에 나타난 의문의 여성, 애니. 무대 뒤에서 진짜 이야기가 시작된다!",
    "posterUrl": "https://image.tmdb.org/t/p/w500/tIalVuhgwImlTdJ7lbP6pHxrZCD.jpg"
  },
  {
    "movieCd": "20232662",
    "movieNm": "삼악도",
    "openDt": "2026-03-11",
    "genreNm": "공포,미스터리",
    "nationAlt": "한국",
    "director": "채기준",
    "isReRelease": false,
    "overview": "일제강점기, 집단 자살 사건 이후 흔적 없이 사라진 사이비 종교 ‘삼선도’. 사회 고발 프로그램 PD 채소연(조윤서)은 일본 나고야TV 기자 마츠다로부터 ‘피의 예언’만 남긴 채 사라진 이 종교에 대한 제보를 받는다. 한 외딴 마을에서 '삼선도'가 여전히 살아 있으며, 예언을 막기 위한 법사들의 봉인 의식이 진행되고 있었다는 것. 마을에 도착한 취재팀은 그곳에서 이미 ‘피의 예언’이 시작되고 있음을 깨닫게 되는데…",
    "posterUrl": "https://image.tmdb.org/t/p/w500/pOW3ioalNbTjApWkuDvg3DBcdzp.jpg"
  },
  {
    "movieCd": "20258074",
    "movieNm": "아르코",
    "openDt": "2026-03-11",
    "genreNm": "애니메이션,모험,판타지,가족,SF",
    "nationAlt": "프랑스",
    "director": "우고 비엔베누",
    "isReRelease": false,
    "overview": "2075년, 자연이 너무 위험해져 아이들은 돔 안에서 생활하고, 부모 없이 로봇에 의해 양육된다. 열 살 소녀 아이리스는 어느 날, 자신이 2932년 미래에서 왔으며 무지개를 타고 하늘을 날 수 있다고 말하는 동갑내기 소년 아르코를 만나며 희망의 빛을 발견하게 된다.",
    "posterUrl": "https://image.tmdb.org/t/p/w500/452fi4x08vqfaFpIEI9fsK7Zs4D.jpg"
  },
  {
    "movieCd": "20261642",
    "movieNm": "오, 발렌타인",
    "openDt": "2026-03-11",
    "genreNm": "다큐멘터리",
    "nationAlt": "한국",
    "director": "홍진훤",
    "isReRelease": false,
    "overview": "2004년 2월 14일, 하청노동자 박일수의 죽음은 한 인간의 죽음이자 뜨거웠던 민주노조운동의 죽음이었다. 패배한 혁명의 그 날로부터 20여 년이 지난 지금, 그가 간절히 바랐던 세상을 꿈꾸며 예술을 이어가는 두 사람이 있다. 노동에서 생태로, 여성으로, 그리고 우리 삶의 위태로운 구석구석으로 패배한 과거의 혁명을 시와 노래로 이어가고 있다. 두 개의 영상, 중첩되는 사운드, 과거와 현재... 분할된 기록의 틈새 속에서 새로운 혁명의 모습을 찾아낸다.",
    "posterUrl": "https://image.tmdb.org/t/p/w500/wcep9u6PjHJBungbaIM7uV3ebJr.jpg"
  },
  {
    "movieCd": "20261596",
    "movieNm": "콜드 미트",
    "openDt": "2026-03-11",
    "genreNm": "스릴러,공포",
    "nationAlt": "영국",
    "director": "Sébastien Drouin",
    "isReRelease": false,
    "overview": "크리스마스를 며칠 앞둔 혹한의 밤, 길가의 식당을 들른 ‘데이비드’는 웨이트리스 '애나'를 폭력 남편으로부터 구하고 다시 길을 나선다. 얼마 후 맹렬히 추격하며 위협을 가하는 트럭 한 대 가까스로 피한 것도 잠시, 차가 고랑에 빠져 고립되고 마는데..",
    "posterUrl": "https://image.tmdb.org/t/p/w500/iIbqGf48qtREH1gKrqKywegM87f.jpg"
  },
  {
    "movieCd": "20261927",
    "movieNm": "스페셜즈",
    "openDt": "2026-03-13",
    "genreNm": "코미디,액션,음악",
    "nationAlt": "일본",
    "director": "우치다 에이지",
    "isReRelease": false,
    "overview": "\"목표는 핵심 인물 암살, 특기는 살인, 임무는 댄스 대회 챌린지?!” 스페셜한 목표를 가진 5명의 킬러들의 죽여주는 전대미문의 댄스 액션 무비",
    "posterUrl": "https://image.tmdb.org/t/p/w500/bDr7PyYyK5mRp1da2ZOsJYyj81A.jpg"
  },
  {
    "movieCd": "20261905",
    "movieNm": "우주 수호대: 하하하 행성의 대모험",
    "openDt": "2026-03-13",
    "genreNm": "애니메이션,모험,판타지,가족",
    "nationAlt": "중국",
    "director": "Peng Liu",
    "isReRelease": false,
    "overview": "'지구를 공룡 세상으로 만들고 말거야!' 레이지맨 박사가 이끄는 공룡몬의 습격으로 우주 수비대 대장 ‘썬더’와 함께 블루 타이거 마을이 사라진다. 10년 후 아빠 '스톰'의 뒤를 이어 ‘우주 수호대’의 대장으로 성장한 ‘스톰’은 새로운 공룡몬의 공격을 받게 되고 이를 좇던 중 아빠 ‘썬더’와 타이거 마을이 행방을 찾게 된다. 또 다시 사악한 음모를 꾸미는 레이지맨 박사에 맞서 지구를 지킬 수 있을까? 우주 수호대! 공룡몬을 막으러 출동!",
    "posterUrl": "https://image.tmdb.org/t/p/w500/8sdaqv5ijEhs4sxPDJwiCMJhlT6.jpg"
  },
  {
    "movieCd": "20258158",
    "movieNm": "극장의 시간들",
    "openDt": "2026-03-18",
    "genreNm": "드라마",
    "nationAlt": "한국",
    "director": "이종필",
    "isReRelease": false,
    "overview": "[침팬지] “영화는 오랜 친구와 같은 것이다” 2000년 광화문. 고도, 모모, 제제는 영화를 사랑한다는 공통점으로 단짝이 된다. 헌책방에서 신기한 침팬지 이야기를 발견한 세 사람은 그 이야기에 빠져든다. 2025년, 영화감독이 된 고도는 홀로 광화문을 걷다가 다시 침팬지 이야기를 만난다. [자연스럽게] “자, 편안하고 자연스럽게! 레디…액션!” 무더운 여름의 영화 촬영 현장. 어린이 배우들은 동네 곳곳을 뛰어다니며 신나게 노는 장면을 연기 중이다. 그런데 감독은 계속 더 자연스럽게 연기해달라고 말하고, 배우와 스탭들은 고민에 빠진다. “도대체 자연스러운 연기란 뭘까?” [영화의 시간] “너야말로 안 변했네. 그 시절 얼굴이 그대로야” 춘천에 사는 영화는 오랜만에 광화문을 찾는다. 홀로 정동과 광화문 곳곳을 걷다가 우연히 들어간 극장에서 수십 년 만에 여고 동창과 재회한다. 영화는 그곳에서 일하는 동창의 배려로 한여름의 꿈 같은 영화 한 편을 만난다.",
    "posterUrl": "https://image.tmdb.org/t/p/w500/y1A3QozphXefSNjkPdby9K6mZ9v.jpg"
  },
  {
    "movieCd": "20261437",
    "movieNm": "녹나무의 파수꾼",
    "openDt": "2026-03-18",
    "genreNm": "애니메이션,드라마,미스터리,판타지",
    "nationAlt": "일본",
    "director": "이토 토모히코",
    "isReRelease": false,
    "overview": "거절할 수 없는 제안을 받아들이고 영문도 모른 채 소원을 비는 녹나무의 파수꾼이 된 레이토. 그는 초승달과 보름달이 뜨는 날 나무를 찾아오는 심야의 방문객들을 만나며 녹나무에는 세상에 알려지지 않은 특별한 힘이 있다는 것을 알게 된다. 오래된 예약 장부를 정리하던 레이토는 이곳을 찾는 사람들과 녹나무의 연결 고리를 발견하고 자신이 파수꾼이 된 이유와 녹나무에 얽힌 놀라운 진실에 다가가게 되는데...",
    "posterUrl": "https://image.tmdb.org/t/p/w500/iS2nH80GEv2OsDAJ48OrqojPVIU.jpg"
  },
  {
    "movieCd": "20259553",
    "movieNm": "드림스",
    "openDt": "2026-03-18",
    "genreNm": "로맨스,스릴러,드라마",
    "nationAlt": "미국",
    "director": "미셸 프랑코",
    "isReRelease": false,
    "overview": "멕시코 출신의 젊고 매력적인 무용수 ‘페르난도’는 성공한 자선사업가이자 연인인 미국인 ‘제니퍼’와 함께할 아메리칸 드림을 꿈꾸며 불법 입국을 감행한다. 그러나, 제니퍼는 미국 상류사회에서 자신의 자리를 지키기 위해 페르난도와 연인임을 숨기게 되고, 두 사람 사이에 서서히 균열이 생기기 시작하는데…",
    "posterUrl": "https://image.tmdb.org/t/p/w500/HSSJhvMayrfXap4QIzokzNsjwU.jpg"
  },
  {
    "movieCd": "20241575",
    "movieNm": "메소드연기",
    "openDt": "2026-03-18",
    "genreNm": "코미디,드라마",
    "nationAlt": "한국",
    "director": "이기혁",
    "isReRelease": false,
    "overview": "코미디 알계인으로 뜨고 알계인으로 기억되는 배우 이동휘. 더 이상 웃기는 연기가 하기 싫은 그는 모든 활동을 중단한 채 연기 변신의 기회만을 기다린다. 오랜 공백 끝, 톱스타 정태민의 차기작 사극 경화수월에 임금 역으로 캐스팅된 이동휘는 메소드 연기를 보여주겠다는 각오를 다지며 공개 금식까지 단행한다. 하지만 첫 촬영부터 NG 연발, 바지 속에 숨겨둔 삼각김밥이 들통나는 굴욕이 이어지고 설상가상 매니저 대신 따라온 형 이동태의 현장 난입과 정태민과의 기싸움 그리고 무리한 대본 수정까지 겹치며 촬영 현장은 점점 통제 불능 상태로 치닫는데…",
    "posterUrl": "https://image.tmdb.org/t/p/w500/qbZitRjnObttv0rgI3I4HMpjWgN.jpg"
  },
  {
    "movieCd": "20261804",
    "movieNm": "폭탄",
    "openDt": "2026-03-18",
    "genreNm": "스릴러,미스터리",
    "nationAlt": "일본",
    "director": "나가이 아키라",
    "isReRelease": false,
    "overview": "“앞으로 세 번, 다음 폭발은 한 시간 뒤입니다.” 그의 말을 놓치는 순간, 연쇄 폭발은 현실이 된다. 모든 시작은 술에 취한 채 연행된 지극히 평범해 보이는 중년 남성 ‘스즈키’의 한마디였다. 대수롭지 않게 여겨진 그의 예언은 한 시간 뒤, 실제 도쿄 도심에서 발생한 폭발로 현실이 되고 경시청 수사 1과의 형사 ‘루이케’는 ‘스즈키’를 핵심 용의자로 판단, 그를 밀실의 취조실에 가둔 채 심문을 이어간다. 도쿄 전역을 누비는 폭탄 수색과 취조실에서 벌어지는 치열한 심리전 속에서 수사관들은 이 미스터리에 숨겨진 진실과 마주하게 되는데…",
    "posterUrl": "https://image.tmdb.org/t/p/w500/1frHgT6vu74eJv30q1dZaVkURWk.jpg"
  },
  {
    "movieCd": "20261782",
    "movieNm": "프로젝트 헤일메리",
    "openDt": "2026-03-18",
    "genreNm": "SF,모험",
    "nationAlt": "미국",
    "director": "필 로드",
    "isReRelease": false,
    "overview": "눈을 떠보니 아득한 우주의 한가운데에서 깨어난 중학교 과학교사 그레이스는 희미한 기억 속에서 자신이 죽어가는 태양으로부터 지구와 인류를 살릴 마지막 희망으로 이곳에 왔다는 사실을 알게 된다. 잃어버린 기억으로 인해 모든 것이 혼란스러운 상황에서 그레이스는 우연히 우주 한복판에서 같은 목적으로 온 뜻밖의 존재 로키를 만나게 되고 그레이스와 로키는 각 두 행성의 운명을 건 마지막 미션을 수행하러 떠나게 되는데…",
    "posterUrl": "https://image.tmdb.org/t/p/w500/qqGpVVZk2KD1lAvccgTU4Z6nh1H.jpg"
  },
  {
    "movieCd": "20262137",
    "movieNm": "하이재킹: 메이데이",
    "openDt": "2026-03-18",
    "genreNm": "스릴러,액션,범죄",
    "nationAlt": "베트남",
    "director": "함 트란",
    "isReRelease": false,
    "overview": "1978년 베트남, 다낭에서 출발한 여객기가 이륙 직후 무장 괴한들에게 점령당한다. 납치범들의 수장은 비행기를 돌릴 것을 요구하며 승객들을 인질로 잡고 기내를 공포로 몰아넣는다. 30,000피트 상공, 폐쇄된 기내, 한정된 연료. 목표는 하나. 무사히 착륙해야 한다!",
    "posterUrl": "https://image.tmdb.org/t/p/w500/xxY2tRUkDGrAIAw6RV7umX1kwhx.jpg"
  },
  {
    "movieCd": "20251809",
    "movieNm": "그 사람 경허(鏡虛) 선사",
    "openDt": "2026-03-19",
    "genreNm": "드라마,역사",
    "nationAlt": "한국",
    "director": "윤용진",
    "isReRelease": false,
    "overview": "근현대 불교를 개창하고 선종을 중흥시킨 경허(鏡虛, 1849~1912) 대선사에 관한 작품",
    "posterUrl": "https://image.tmdb.org/t/p/w500/3vA4WlXMk0cMo5xAI8CCMV0xhe.jpg"
  },
  {
    "movieCd": "20250339",
    "movieNm": "김~치!",
    "openDt": "2026-03-25",
    "genreNm": "드라마",
    "nationAlt": "한국",
    "director": "박철현",
    "isReRelease": false,
    "overview": "퇴직과 이별로 마음의 자리를 잃어버린 ‘민경’은 작은 시골마을로 내려와 조용히 사진을 찍으며 지내기 시작한다. 사람보다 풍경을, 감정보다 거리를 두던 그녀의 카메라에 어느 날 한 노인이 들어온다. 치매를 앓고 있는 베트남 참전용사 ‘덕구’. 손녀를 교통사고로 잃은 뒤 기억이 조금씩 희미해지고 있는 그는, 매일 아침 집 앞에 앉아서 죽은 손녀를 향해 손을 흔드는 치매를 앓고있지만,. 사진을 찍는 순간만큼은 누구보다 또렷한 눈빛으로 카메라를 바라본다. 우연처럼 시작된 기록은 점점 ‘민경’의 하루가 되고, 덕구가족의 사연을 알게 되고 덕구의 잃어가는 기억을 붙잡아주려는 시간은 어느새 민경 자신의 상처를 어루만지고 치유받는 시간이 된다. 기억을 잃어가는 사람과, 삶의 방향을 잃어버린 사람. 서로 다른 상처를 가진 두 사람이 사진을 교감으로 미소를 되찾고 조금씩 마음을 나누기 시작한다. 그리고 마침내, 덕구가 민경의 마음속에 들어와 가장 환하게 울려 퍼지는 한마디. “김~치!” 그 한 장의 사진처럼, 두 사람의 시간도 다시 또렷해진다.",
    "posterUrl": "https://image.tmdb.org/t/p/w500/bg9GrjrN8cXb7gF5lcglcwKlwYk.jpg"
  },
  {
    "movieCd": "manual_20260325_lifeofpi",
    "movieNm": "라이프 오브 파이",
    "openDt": "2026-03-25",
    "genreNm": "드라마",
    "nationAlt": "미국",
    "director": "이안",
    "isReRelease": true,
    "overview": "인도에서 동물원을 운영하던 ‘파이’의 가족들은 정부의 지원이 끊기자 캐나다로 이민을 준비한다.  동물들을 싣고 캐나다로 떠나는 배에 탑승한 가족들.  하지만 상상치 못한 폭풍우에 화물선은 침몰하고 가까스로 구명선에 탄 파이만 목숨을 건지게 된다.  구명 보트에는 다리를 다친 얼룩말과 굶주린 하이에나,  그리고 바나나 뭉치를 타고 구명보트로 뛰어든 오랑우탄이 함께 탑승해 긴장감이 감돈다.  하지만 이들 모두를 놀라게 만든 진짜 주인공은  보트 아래에 몸을 숨기고 있었던 벵갈 호랑이 ‘리처드 파커’!  시간이 갈수록 배고픔에 허덕이는 동물들은 서로를 공격하고  결국 리처드 파커와 파이만이 배에 남게 된다.  파이는 배에서 발견한 생존 지침서를 바탕으로  점차 ‘리처드 파커’와 함께 바다 위에서 살아가는 법을 습득하게 된다.  그리고 태평양 한가운데서..  집채 만한 고래와 빛을 내는 해파리, 하늘을 나는 물고기, 그리고 미어캣이 사는 신비의 섬 등  그 누구도 보지 않고서는 믿을 수 없는 놀라운 사건들을 겪게 되는데…!",
    "posterUrl": "https://image.tmdb.org/t/p/w500/mexaTje46m4uJ9YToFUydtZuqaL.jpg"
  },
  {
    "movieCd": "20253247",
    "movieNm": "사랑, 우유, 그리고 치즈",
    "openDt": "2026-03-25",
    "genreNm": "드라마,코미디",
    "nationAlt": "프랑스",
    "director": "Louise Courvoisier",
    "isReRelease": false,
    "overview": "평범한 열여덟 살 시골 소년 또똔느는 친구들과 파티를 즐기며 하루하루를 보낸다. 하지만 아버지가 갑작스러운 교통사고로 세상을 떠나면서 그의 삶은 완전히 뒤바뀐다. 일곱 살 여동생을 혼자 돌봐야 하고, 스스로 생계를 책임져야 하는 또똔느. 그가 선택한 방법은 단 하나, 치즈 만들기 경연대회에 나가 이 지역 최고의 콩테 치즈를 만드는 것!",
    "posterUrl": "https://image.tmdb.org/t/p/w500/1pdQncvITi6aPTnhJ4zXvdve3KN.jpg"
  },
  {
    "movieCd": "manual_20260325_soundofmusic",
    "movieNm": "사운드 오브 뮤직",
    "openDt": "2026-03-25",
    "genreNm": "뮤지컬",
    "nationAlt": "미국",
    "director": "로버트 와이즈",
    "isReRelease": true,
    "posterUrl": "https://image.tmdb.org/t/p/w500/3l1ATCYNuHep6evzX8GSUigWOLs.jpg",
    "overview": "알프스의 아름다운 자연에 둘러싸인 오스트리아의 잘츠부르크 수도원. 음악을 사랑하는 말괄량이 견습 수녀 마리아는 원장 수녀의 권유로 해군 명문 집안 폰 트랩가의 가정교사가 된다. 마리아는 좀처럼 마음의 문을 열지 않는 폰 트랩가의 일곱 아이들에게 노래를 가르치며 점차 교감하게 되고, 엄격한 폰 트랩 대령 역시 마음의 문을 열게 된다. 그러던 어느 날, 마리아는 자신이 폰 트랩 대령을 사랑하고 있다는 사실을 깨닫게 되고, 자신만의 비밀을 간직한 채 아이들의 곁을 떠나 다시 수녀원에 들어가기로 결심하는데..."
  },
  {
    "movieCd": "19868242",
    "movieNm": "연지구 디 오리지널 4K",
    "openDt": "2026-03-25",
    "genreNm": "드라마,판타지,로맨스,미스터리",
    "nationAlt": "홍콩",
    "director": "관금붕",
    "isReRelease": false,
    "overview": "1934년 홍콩, 부유한 가문의 자제 진진방과 기생 여화는 신분을 초월한 사랑을 하지만, 가문의 반대에 부딪히자 저승에서의 재회를 약속하며 동반 자살을 선택한다. 50년 후, 약속한 시간이 지나도 오지 않는 연인을 찾기 위해 여화는 유령이 되어 1980년대 홍콩을 다시 찾아오는데…",
    "posterUrl": "https://image.tmdb.org/t/p/w500/cC6U0pVzlkZcV6htkdEl8xlz3iG.jpg"
  },
  {
    "movieCd": "20233613",
    "movieNm": "열여덟 청춘",
    "openDt": "2026-03-25",
    "genreNm": "드라마",
    "nationAlt": "한국",
    "director": "어일선",
    "isReRelease": false,
    "overview": "규칙보다 아이들의 ‘다름’을 먼저 보는 ‘별난 선생님’ 희주가 새로 부임한다. 반장도 사물함도 돌아가며 맡고, 휴대폰도 자율에 맡기자는 그의 파격 제안에 교실은 금세 한결 자유롭고 생기 있게 바뀐다. 하지만 그런 변화가 모두 반가운 것만은 아니다. 동료 교사들은 불안해하고, 뭐든 반듯해야 하는 우등생 경희는 고개를 갸웃한다. 한편, 엄마와 단둘이 사는 열여덟 순정은 집도 학교도 답답한 영락없는 사춘기 소녀. 졸업 후 아프리카로 떠나겠다는 엉뚱하지만 진지한 꿈을 품고 스와힐리어를 공부하며 차곡차곡 ‘탈출 계획’을 세우는 중이다. 그런 순정에게 자꾸만 다가오는 존재, 바로 오지랖 넓은 담임 희주. 그 관심이 귀찮기만 하다. 자유를 믿는 선생님, 벗어나고 싶은 학생, 흔들리면 안 된다고 믿는 우등생. 서로 다른 세 사람은 한 교실 안에서 부딪히며 조금씩 서로를 이해하기 시작한다. 그리고 그 만남은, 그들의 열여덟을 조금 다른 방향으로 이끈다.",
    "posterUrl": "https://image.tmdb.org/t/p/w500/a3NLNDQNIRY8m5MVikrImNiHAW3.jpg"
  },
  {
    "movieCd": "20262430",
    "movieNm": "왜(歪): 더 카르텔",
    "openDt": "2026-03-25",
    "genreNm": "다큐멘터리",
    "nationAlt": "한국",
    "director": "Lee Seung-hwan",
    "isReRelease": false,
    "overview": "<왜(歪): 더 카르텔>은 2020년 4.15 총선에서 드러난 각종 통계적·물적 증거를 심도 있게 분석한 충격적인 부정선거 다큐멘터리 영화로 배우 겸 성우 윤주상 님이 내레이션을 맡았습니다. 믿기지 않고 믿고 싶지도 않은 끔찍한 부정선거는 비단 4.15 총선뿐만이 아니라 정권이 바뀐 후에도 여전히 계속되고 있습니다. 부디 이 작품을 통해 천인공노할 충격적인 부정선거의 실상이 널리 알려지기를 기원합니다.",
    "posterUrl": "https://image.tmdb.org/t/p/w500/2SlDNGoIFNIR8B80cVwHL8LelWv.jpg"
  },
  {
    "movieCd": "20257521",
    "movieNm": "프로텍터",
    "openDt": "2026-03-25",
    "genreNm": "액션,스릴러",
    "nationAlt": "한국",
    "director": "애드리언 그런버그",
    "isReRelease": false,
    "overview": "미 특수부대에서 뛰어난 활약상을 보이며 국가를 위해 헌신했던 니키는 딸의 어린 시절을 함께 보내지 못했다. 남편이 사망한 후, 그녀는 딸 클로이 곁으로 돌아온다. 그러나 떨어져 지냈던 시간의 공백만큼 두 모녀 사이의 틈은 좁혀질 기미가 보이지 않는다. 클로이는 16번째 생일날 외출을 했다가 납치를 당하고, 니키는 거대 조직에 맞서 72시간 안에 딸을 되찾아야 하는 위험천만한 상황에 처한다. 경찰과 군대는 니키를 표적으로 삼고, 시간은 잔인하게 흐른다.",
    "posterUrl": "https://image.tmdb.org/t/p/w500/kJvFZt7x3VWOtMQwANwXGD59ArJ.jpg"
  },
  {
    "movieCd": "20262291",
    "movieNm": "뮤지컬 장수탕 선녀님",
    "openDt": "2026-03-26",
    "genreNm": "판타지,가족",
    "nationAlt": "한국",
    "director": "조윤수",
    "isReRelease": false,
    "overview": "백희나 작가의 스테디셀러 그림책을 원작으로 오랜 시간 사랑받아온 가족 뮤지컬 '장수탕 선녀님'이 무대 위 에너지에 영화적 연출을 더해 대형 스크린에서 새롭게 펼쳐진다. 웃음과 따뜻함, 그리고 추억이 만나는 순간! 아이와 어른이 함께 공감하는 신비로운 장수탕의 이야기가 다시 시작된다.",
    "posterUrl": "https://image.tmdb.org/t/p/w500/rszzeXaj3A3yyEPhmh9440mIy3p.jpg"
  },
  {
    "movieCd": "20255361",
    "movieNm": "파이 굽는 엄마",
    "openDt": "2026-03-26",
    "genreNm": "다큐멘터리",
    "nationAlt": "한국",
    "director": "이종은",
    "isReRelease": false,
    "overview": "김요한 목사는 매주 월요일,두 시간 반 거리에 있는 수원 어머님 집을 찾는다. 그의 어머니는 중앙기독유치원의 원장을 지낸 트루디(85세. 한국이름: 김추리)여사. 2006년 혈액암의 일종인 다발성 골수종으로 척추 수술을 받은 후 10년 전 암이 재발하여 항암치료를 받던 중 치매 증상까지 겹쳐 모든 외부활동을 접고 휠체어 생활을 하고 있다. 이민 1세대로 사회적 편견을 극복하고 3남매를 훌륭히 키워낸 김추리 여사는 1979년 중앙기독유치원을 설립하고 장애인 통합교육을 실천, 15년간 수원여자교도소에서 영어를 가르치고 최근까지 장애인들을 돕기 위해 파이가게를 운영하는 등 약자들을 위해 평생을 살아왔다.",
    "posterUrl": "https://image.tmdb.org/t/p/w500/mSt2VLGwBUuFLZX7jul2wMPeTiu.jpg"
  },
  {
    "movieCd": "20261906",
    "movieNm": "명탐정 코난: 세기말의 마술사",
    "openDt": "2026-03-27",
    "genreNm": "모험,애니메이션,범죄,드라마,미스터리",
    "nationAlt": "일본",
    "director": "코다마 켄지",
    "isReRelease": false,
    "overview": "러시아 로마노프 왕조의 유산인 파베르제의 달걀 중 세기말 최후의 보물 ‘메모리즈 에그’가 발견되고, 이를 노리는 괴도 키드의 예고장이 도착한다. 그를 막기 위해 괴도 키드 특별 수사팀과 코난 일행, 서쪽의 고등학생 탐정 핫토리까지 합류한다. 신출귀몰한 괴도 키드는 모두를 따돌리며 ‘메모리즈 에그’를 훔치는 데 성공하지만, 정체불명의 누군가에게 저격당해 행방불명된다. 무사히 달걀을 되찾은 코난은 ‘메모리즈 에그’에 담긴 수수께끼를 발견한다. 달걀의 비밀을 풀기 위해 크루즈를 타고 도쿄로 향하는 코난 일행, 그러나 배 안에서 의문의 살인 사건이 발생하고 진실은 미궁에 빠지는데…",
    "posterUrl": "https://image.tmdb.org/t/p/w500/mGBjQkACdChVakczn92CfaqWQJH.jpg"
  },
  {
    "movieCd": "20262179",
    "movieNm": "펫 트레인",
    "openDt": "2026-03-28",
    "genreNm": "애니메이션,코미디,모험,스릴러",
    "nationAlt": "프랑스",
    "director": "Benoît Daffis,Jean-Christian Tassy",
    "isReRelease": false,
    "overview": "도심 속 동물 평화를 수호하는 정의의 너구리 ‘팔콘’! 배고픈 동물 친구들을 위해 열차에 오르는 순간, 복수심에 불타는 오소리 ‘한스’에 의해 반려동물들만 탑승한 열차가 브레이크 없이 폭주하기 시작한다. 정면 충돌까지 남은 시간은 단 몇 분! 일촉즉발의 위기 속에서 ‘팔콘’은 새로 만난 친구들과 힘을 합쳐 생존을 위한 스릴 만점의 탈출 작전에 나서는데…",
    "posterUrl": "https://image.tmdb.org/t/p/w500/8GIxRi789MUuF77rV98OK48qnJQ.jpg"
  },
  {
    "movieCd": "20261666",
    "movieNm": "네가 마지막으로 남긴 노래",
    "openDt": "2026-04-01",
    "genreNm": "로맨스,음악",
    "nationAlt": "일본",
    "director": "미키 타카히로",
    "isReRelease": false,
    "posterUrl": "https://image.tmdb.org/t/p/w500/sOGzrv0BM5ezVOz1xP8leVPMZzh.jpg",
    "overview": "유난히 눈에 띄지 않는 소년 ‘하루토’와 유난히 빛나는 소녀 ‘아야네’. 글을 읽고 쓰는 데 어려움이 있는 소녀를 대신해 소년은 시를 쓰고, 그 시는 노래가 되어 소녀의 목소리로 세상에 울려 퍼진다. 둘만의 비밀, 오직 둘만의 언어. 말보다 음악이 먼저 닿은 순간, 설렘으로 시작되는 가장 찬란한 청춘 로맨스!"
  },
  {
    "movieCd": "20259598",
    "movieNm": "두 검사",
    "openDt": "2026-04-01",
    "genreNm": "드라마,미스터리,스릴러,역사",
    "nationAlt": "프랑스,독일,네덜란드",
    "director": "세르게이 로즈니차",
    "isReRelease": false,
    "posterUrl": "https://image.tmdb.org/t/p/w500/wau82xY0mui2JXLCZK9sti3TioS.jpg",
    "overview": "스탈린 시기의 소련, 자신이 하는 일에 갈등을 느끼는 한 젊은 검사의 이야기. 게오르기 데미도프의 중편을 각색한 작품."
  },
  {
    "movieCd": "20261731",
    "movieNm": "류이치 사카모토: 다이어리",
    "openDt": "2026-04-01",
    "genreNm": "다큐멘터리,음악",
    "nationAlt": "일본",
    "director": "Kensho Omori",
    "isReRelease": false,
    "posterUrl": "https://image.tmdb.org/t/p/w500/m82qaGFsfORJNbMM4aY0EvBJM1G.jpg",
    "overview": "전자음악의 선구자이자 영화음악 거장, 환경과 평화를 외치는 운동가로 활약해온 전방위의 아티스트 류이치 사카모토. 2020년 12월, 그는 자신의 시간이 얼마 남지 않았다는 것을 알게 되고 일상을 기록하기 시작한다. 마지막까지 음악으로 살아있던 류이치 사카모토의 모든 순간."
  },
  {
    "movieCd": "20262653",
    "movieNm": "마법 숲 동물 친구들 대모험",
    "openDt": "2026-04-01",
    "genreNm": "애니메이션,판타지,모험",
    "nationAlt": "아랍에미리트연합국정부",
    "director": "Farzad Dalvand,Kianoush Dalvand",
    "isReRelease": false,
    "posterUrl": "https://image.tmdb.org/t/p/w500/gYBZICAItWhdmYNyL9yupUwTQnp.jpg",
    "overview": "사랑스러운 염소 3남매 망굴, 샹굴, 해베이는 수련을 위해 마법의 숲 도장에 가게 되고 거기서 새로운 친구인 토끼 버니 밥과 하마 알비노를 만나게 된다. 큰뿔 사부에게 신비로운 권법을 배우기 위해 마을 바깥 숲에 다녀오는 테스트를 받게 되면서, 은둔해서 살고 있는 검은 늑대의 표적이 되는데..!"
  },
  {
    "movieCd": "20262053",
    "movieNm": "소녀심판",
    "openDt": "2026-04-01",
    "genreNm": "코미디,액션",
    "nationAlt": "한국",
    "director": "류광현",
    "isReRelease": false,
    "overview": "주먹 하나로 학교를 평정한 여고생, 이번엔‘추리닝’입고 돌아왔다! 강한 의협심과 맷집을 지닌‘민아’는 어릴 적 사고로 부모를 잃고 이모집에서 자란, 좀 과하게 정의로운 소녀다. ‘다시는 싸우지 않겠다’는 약속으로 고등학교에 입학한 민아는 평범한 새 출발을 꿈꾸지만, 첫날부터 잘생기고 괜히 정의로워보아는 짝꿍‘민기’에게 꽂힌다. 문제는 민기를 노리는 불량 일진서클의 우두머리‘세혁’. 민기를 괴롭히는 세혁의 패거리를 본 민아는 참다못해‘얼굴가린추리닝차림’으로 민기를 구출해버린다. 이날 이후 학교는 추리닝남의 정체를 찾기 위해 들썩이고, 민기는 구세주를 찾기 위한 본격 추리(?)에 나선다. 한편 민기를 사이에 둔 민아-혜리-세혁의 삼각전투구도에 불이 붙고, 민아는 자신의 정체를 숨기며 평범한척+불한측+사랑에 빠진 척 삼중생활을 하기된다. 그러나 정의감 폭발에 다혈질까지 얹힌 민아에게 그게 가능 할리가? 사랑은 꼬이고, 정체는 탄로날 위기, 싸움은 점점 커지는데…",
    "posterUrl": "https://image.tmdb.org/t/p/w500/mFD8LuQ6XVHhJt0knkdx7k5quLs.jpg"
  },
  {
    "movieCd": "20243842",
    "movieNm": "술타나의 꿈",
    "openDt": "2026-04-01",
    "genreNm": "애니메이션,드라마",
    "nationAlt": "스페인",
    "director": "Isabel Herguera",
    "isReRelease": false,
    "posterUrl": "https://image.tmdb.org/t/p/w500/aytXJNkcJU0NV294OoN96ARCKoa.jpg",
    "overview": "스페인 여성 ‘이네스’는 인도 여행 중 100년 전 최초의 페미니즘 SF 소설 『술타나의 꿈』을 읽고, 여성이 세상을 이끄는 유토피아 ‘레이디랜드’에 매료된다. 소설 속 세계를 따라가듯, 이네스는 인도 전역을 여행하며 점차 자신의 삶과 현실을 새롭게 바라보기 시작한다."
  },
  {
    "movieCd": "20262661",
    "movieNm": "스크림 7",
    "openDt": "2026-04-01",
    "genreNm": "공포,미스터리,범죄",
    "nationAlt": "미국",
    "director": "케빈 윌리엄슨",
    "isReRelease": false,
    "posterUrl": "https://image.tmdb.org/t/p/w500/gqgBqxyr8tGQGJCFrRWAzfA7Cml.jpg",
    "overview": "시드니 프레스콧이 새롭게 정착한 조용한 마을에 새로운 고스트페이스가 등장한다. 그녀의 딸, 테이텀이 다음 표적이 되면서 우려했던 공포가 현실이 되고, 가족을 지키기 위해 시드니는 과거의 공포와 맞서 피의 학살을 영원히 끝내기로 결심하는데…"
  },
  {
    "movieCd": "20262101",
    "movieNm": "킬 빌: 더 홀 블러디 어페어",
    "openDt": "2026-04-01",
    "genreNm": "액션,범죄",
    "nationAlt": "미국",
    "director": "쿠엔틴 타란티노",
    "isReRelease": false,
    "posterUrl": "https://image.tmdb.org/t/p/w500/je5CQCCvXoAhWAwi6MoCai8IFwC.jpg",
    "overview": "23년 만에 공개되는 완전판, 275분 동안 펼쳐지는 완벽한 복수의 향연! 최고의 암살자였던 키도는 빌과 그의 조직인 데들리 바이퍼스로 인해, 끔찍한 피의 결혼식을 겪게 된다. 그리고 4년 후, 이제 그녀에게 남은 것은 자비 없는 복수뿐. 빌을 죽여라!"
  },
  {
    "movieCd": "manual_20260401_farewellmyconcubine",
    "movieNm": "패왕별희",
    "openDt": "2026-04-01",
    "genreNm": "드라마",
    "nationAlt": "중국",
    "director": "첸 카이거",
    "isReRelease": true,
    "overview": "어려서 북경 경극학교에 맡겨진 두지와 시투는 노력 끝에 최고의 경극배우가 된다. 여자 역할을 맡았던 두지는 시투를 흠모하게 되는데, 시투에게 사랑하는 여인 주샨이 생기면서 방황을 한다. 두지는 아편에 손을 대고, 시투는 주샨에게 빠져 산다. 이를 시작으로 두 남자는 중국의 역사처럼 파란만장한 삶을 시작한다.",
    "posterUrl": "https://image.tmdb.org/t/p/w500/8clihqiXW4NDgilMWU3olcfNW1G.jpg"
  },
  {
    "movieCd": "20192680",
    "movieNm": "끝장수사",
    "openDt": "2026-04-02",
    "genreNm": "코미디,범죄,액션",
    "nationAlt": "한국",
    "director": "박철환",
    "isReRelease": false,
    "posterUrl": "https://image.tmdb.org/t/p/w500/5Ae26RGA7hLe4yYsjH0Q9PYCTLN.jpg",
    "overview": "한때 잘 나가던 광역수사대 에이스였지만 사건 말아먹고 인생도 꼬인 형사 재혁에게 명석한 두뇌, 돈과 패기로 무장한 인플루언서 출신 신입 형사 중호가 파트너로 낙점된다. 어느 것 하나 맞지 않던 두 사람은 어느 날, 시골 교회 헌금함에서 48,700원을 훔친 절도범을 검거하고 그가 서울 강남 살인사건의 유력 용의자임을 밝혀낸다. 그러나 이미 범인이 체포되고 사건은 종결된 상황. 진범을 잡기 위해 서울로 출장을 떠난 이들은 담당 검사 미주의 재수사 지원을 약속받고 강남 경찰서에 공조를 요청하지만 팀웍인지 팀킬인지 모를 이들의 태도에 사건은 난관에 봉착하는데…"
  },
  {
    "movieCd": "20256103",
    "movieNm": "모래그릇",
    "openDt": "2026-04-02",
    "genreNm": "범죄,미스터리,드라마",
    "nationAlt": "일본",
    "director": "Yoshitarō Nomura",
    "isReRelease": false,
    "posterUrl": "https://image.tmdb.org/t/p/w500/2zB5ySojpqPd3rEGWzc32bCDLi1.jpg",
    "overview": "도쿄역 차량기지 선로에서 얼굴이 짓 뭉개진 60대 신원불명의 변사체가 발견된다. 경찰은 즉각 수사본부를 설치하고 현장에서 발견된 술집 상호가 인쇄된 성냥곽을 단서로 탐문 수사를 시작한다 그리고 술집 여종업원으로부터 피해자와 어떤 젊은 남자가 방문했고 그들로부터 언뜻 \"가메다\" 라는 말을 했다는 증언을 듣게 되지만 그것이 무엇을 뜻하는지 도무지 알 수가 없어 수사는 미궁으로 빠지는데…"
  },
  {
    "movieCd": "20262463",
    "movieNm": "오피셜히게단디즘 라이브 앳 스타디움 2025",
    "openDt": "2026-04-02",
    "genreNm": "음악,다큐멘터리",
    "nationAlt": "일본",
    "director": "Hiroko Ishizuchi",
    "isReRelease": false,
    "posterUrl": "https://image.tmdb.org/t/p/w500/g4Y9OrdmssvUsxawfGb1zOVwTeL.jpg",
    "overview": "2025년 초여름, 일본을 열광시킨 오피셜히게단디즘의 첫 스타디움 투어. 25만 명이 함께 느꼈던 환희와 전율이 스크린에서 되살아난다! 후지하라 사토시, 오자사 다이스케, 나라자키 마코토, 마츠우라 마사키. 네 사람이 만들어내는 압도적인 밴드 사운드와 감정을 파고드는 음악은 스타디움을 가득 채웠던 그날의 열기와 울림을 생생하게 불러온다. 데뷔 10주년을 맞이한 네 사람의 지난 여정과 음악을 향한 진심, 그리고 팬들과 이어져 온 시간들이 비로소 하나의 이야기로 완성되는 기록."
  },
  {
    "movieCd": "20262327",
    "movieNm": "특별편집판 기동전사 건담 철혈의 오펀스 우르드 헌트 -작은 도전자의 궤적-",
    "openDt": "2026-04-04",
    "genreNm": "액션,애니메이션,SF",
    "nationAlt": "일본",
    "director": "나가이 타츠유키",
    "isReRelease": false,
    "posterUrl": "https://image.tmdb.org/t/p/w500/421VGMl4eDmdI4EdElnSuSCVX62.jpg",
    "overview": "“축하드립니다. 당신은 ‘우르드 헌트’의 참가 자격을 얻었습니다.” 화성과의 개척 경쟁에서 패배하고 죄인들의 유배지로 전락한 변방 행성, 금성. 그곳의 라도니차 콜로니에서 나고 자란 소년 위스타리오 아팜은 척박한 고향의 현실을 바꾸고 싶다는 열망을 품고 살아간다. 어느 날, 위스타리오의 앞에 정체불명의 소녀 코르날 코사가 나타나고 그는 콜로니 전체를 살 수 있을 만큼 막대한 상금이 걸린 의문의 레이스 ‘우르드 헌트’에 초대받게 된다. 고향의 운명을 바꾸기 위해, 소년은 전설의 기체 ‘건담 하지로보시’와 함께 한 치 앞도 알 수 없는 거대한 격전의 소용돌이 속으로 뛰어든다."
  },
  {
    "movieCd": "manual_20260408_grandbudapest",
    "movieNm": "그랜드 부다페스트 호텔",
    "openDt": "2026-04-08",
    "genreNm": "드라마",
    "nationAlt": "미국",
    "director": "웨스 앤더슨",
    "isReRelease": true,
    "overview": "1927년 세계대전이 한창이던 어느 날, 세계 최고 부호 마담 D가 그랜드 부다페스트 호텔에 다녀간 지 얼마 지나지 않아 의문의 살인을 당한다. 그녀는 유언을 통해 가문 대대로 내려오던 명화 사과를 든 소년을 전설적인 호텔 지배인이자 연인 구스타브 앞으로 남긴다.  마담 D의 유산을 노리고 있던 그의 아들 드미트리는 구스타브를 졸지에 유력한 용의자로 지목하게 되고, 구스타브는 충실한 호텔 로비보이 제로와 함께 누명을 벗기기 위한 기상천외한 모험을 시작한다.",
    "posterUrl": "https://image.tmdb.org/t/p/w500/vsibrPwiJlZHhlrX5f4xFptX3q4.jpg"
  },
  {
    "movieCd": "manual_20260408_romanholiday",
    "movieNm": "로마의 휴일",
    "openDt": "2026-04-08",
    "genreNm": "로맨스",
    "nationAlt": "미국",
    "director": "윌리엄 와일러",
    "isReRelease": true,
    "posterUrl": "https://image.tmdb.org/t/p/w500/dYLiHwYkoxCZI6bJUik4ZHbMRkc.jpg",
    "overview": "유럽 순방 중 로마를 방문한 공주 ‘앤’. 끝없는 일정에 지쳐버린 그녀는 한밤중 몰래 침실을 빠져나와 처음으로 자유롭게 로마의 거리를 거닌다. 로마에서 생활 중인 미국인 기자 ‘조 브래들리’. 공주와의 인터뷰를 맡게 된 그는 집으로 돌아가는 길에 술에 취해 잠든 한 여성을 발견하고 하룻밤 재워주게 된다. 다음 날, 신문사에 출근한 ‘조’는 공주와의 인터뷰가 돌연 취소됐다는 소식을 듣게 되고, 신문 1면에서 낯익은 얼굴을 마주하게 되는데…"
  },
  {
    "movieCd": "20254121",
    "movieNm": "살목지",
    "openDt": "2026-04-08",
    "genreNm": "공포",
    "nationAlt": "한국",
    "director": "이상민",
    "isReRelease": false,
    "posterUrl": "https://image.tmdb.org/t/p/w500/uVJyWlSPCWftRUXRM6lxTqOzPY6.jpg",
    "overview": "기이한 소문이 끊이지 않는 저수지 살목지의 로드뷰 화면에 촬영한 적 없는 정체불명의 형체가 포착된다. 오늘 안에 반드시 재촬영을 끝내야 하는 상황 속에 살목지로 향한 PD 수인과 촬영팀. 촬영이 시작되자 행방이 묘연했던 선배 교식이 등장하고, 설명되지 않는 일들이 연달아 벌어지며 촬영팀은 점점 아비규환에 빠진다. 휘몰아치는 공포 속 기태는 수인을 향해 내달리지만 빠져나오려 할수록 이들은 점점 더 깊은 곳으로 끌려 들어가게 되는데…"
  },
  {
    "movieCd": "20262710",
    "movieNm": "엔하이픈 : 이머전 인 시네마",
    "openDt": "2026-04-08",
    "genreNm": "음악,다큐멘터리",
    "nationAlt": "한국",
    "director": "김경국",
    "isReRelease": false,
    "posterUrl": "https://image.tmdb.org/t/p/w500/6a7Wwooo0a8BWL6qmqF1kqzZoex.jpg",
    "overview": "25년 7월, ENHYPEN WORLD TOUR ‘WALK THE LINE’ IN JAPAN -SUMMER EDITION-의 모든 순간을 담다. 선 위에서 서로를 만난 일곱 소년. 과거와 현재를 잇는 여정을 지나 각자의 빛을 지닌 일곱 명이 하나의 팀으로 완성된다. 데뷔 1년 만의 밀리언셀러, 최단 기간 도쿄돔 입성이라는 새로운 기록, 그리고 2025년 첫 대상의 영광과 전 세계를 사로잡은 코첼라 무대까지. 그 눈부신 순간 뒤에는 늘 엔진과 함께 만든 ‘연결’의 에너지가 있었다. 엔하이픈과 팬들을 이어주는 보이지 않는 선. 그 위에서 울고 웃으며 하나가 된 순간들, 무대 뒤의 생생한 리허설, 투어를 오가는 이동 속의 일상, 그리고 여름의 도쿄를 가득 채운 뜨거운 숨결까지 모두 스크린에 담아낸다. 그리고 앞으로도 계속 그려질 새로운 선. 미래를 향한 또 하나의 연결. 엔하이픈과 엔진이 함께 써 내려갈 새로운 이야기와 새로운 기록이 지금, 눈앞에서 펼쳐진다."
  },
  {
    "movieCd": "20261622",
    "movieNm": "위 리브 인 타임",
    "openDt": "2026-04-08",
    "genreNm": "로맨스,드라마",
    "nationAlt": "프랑스",
    "director": "존 크로울리",
    "isReRelease": false,
    "posterUrl": "https://image.tmdb.org/t/p/w500/i8HPNRsXx9Cen4CkSWMk94t6gHM.jpg",
    "overview": "본인의 레스토랑 오픈을 준비하며 새로운 도약을 꿈꾸는 셰프 ‘알무트’. 최근 이혼을 하면서 삶의 한 챕터를 끝낸 ‘토비아스’. 예기치 못한 만남을 계기로 두 사람은 서로의 삶을 변화시키는 잊지 못할 10년을 보낸다. 우리의 사랑은 함께한 시간에 영원히 남는다."
  },
  {
    "movieCd": "20262343",
    "movieNm": "크라임 101",
    "openDt": "2026-04-08",
    "genreNm": "범죄,스릴러",
    "nationAlt": "미국",
    "director": "바트 레이튼",
    "isReRelease": false,
    "posterUrl": "https://image.tmdb.org/t/p/w500/77ggpowGO0ORQY9x33NeBIPajm1.jpg",
    "overview": "101번 국도를 따라 흔적도 없이 사라지는 보석들. 전설적인 절도범 ‘데이비스’는 자신만의 규칙 아래 완벽한 범죄를 설계한다. 모두가 혼란에 빠진 사이, 원칙과 집념의 형사 ‘루’만이 범인의 실체를 포착하며 포위망을 좁혀간다. 거대한 보험금을 노린 ‘데이비스’는 보험중개인 ‘샤론’에게 위험한 거래를 제안하고 완벽했던 계획과 정교한 수사는 예상치 못한 국면으로 치닫는데…"
  },
  {
    "movieCd": "manual_20260408_breakfastattiffanys",
    "movieNm": "티파니에서 아침을",
    "openDt": "2026-04-08",
    "genreNm": "로맨스",
    "nationAlt": "미국",
    "director": "블레이크 에드워즈",
    "isReRelease": true,
    "posterUrl": "https://image.tmdb.org/t/p/w500/8U6b8j8wTRsFZ4k57sVOvEwpKkY.jpg",
    "overview": "1940년대 초 뉴욕, 검은 선글라스에 화려한 장신구로 치장한 한 여성이 택시에서 내려 보석상 티파니 앞을 활보한다. 그녀는 뉴욕의 한 아파트에서 홀로 살아가며 부유한 남자들과의 만남을 통해 화려한 신분 상승을 꿈꾸는 홀리. 어느 날 같은 아파트에 폴이라는 별 볼 일 없는 작가가 이사를 오면서 이들의 만남이 시작된다. 폴은 이웃에 사는 우아하고 귀여운 홀리를 보고 매료당하고, 센트럴 파크에서 둘이서 승마를 타기도 하는 등 점점 친해진다. 하지만 그녀는 가난한 현실을 벗어나 꿈같은 상류 사회, 부와 풍요를 동경한다. 신분 상승을 꿈꾸는 그녀에게 폴은 말이 통하는 좋은 친구일 뿐..."
  },
  {
    "movieCd": "20262648",
    "movieNm": "런닝맨: 라이트&쉐도우",
    "openDt": "2026-04-11",
    "genreNm": "애니메이션,가족,액션,모험",
    "nationAlt": "한국",
    "director": "윤준상",
    "isReRelease": false,
    "posterUrl": "https://image.tmdb.org/t/p/w500/khtyZwS1E944FFUlPDEuuyTFbL2.jpg",
    "overview": "수차례에 걸쳐 세상을 구한 런닝맨들은 트리시티의 대스타로 절대적인 지지를 받고 있다. 그러던 어느 날 런닝맨들이 돌연 위험한 악당이 되어 시민들을 공격하기 시작하는데… 1,000년 간 그림자 속에서 세상의 밸런스를 지켜온 비밀 조직 메트로놈은 흑화한 런닝맨을 제거하기 위해 전면전을 선포한다. 메트로놈의 에이전트 레마는 런닝맨의 갑작스런 변화를 수상히 여기며 수사를 시작하고, ‘빛’과 ‘그림자’, 런닝맨과 메트로놈. 서로를 향한 총구를 겨누며 펼쳐지는 역대급 초능력 대결—트리시티의 진짜 적은 과연 누구인가?"
  },
  {
    "movieCd": "20247648",
    "movieNm": "내 이름은",
    "openDt": "2026-04-15",
    "genreNm": "드라마",
    "nationAlt": "한국",
    "director": "정지영",
    "isReRelease": false,
    "posterUrl": "https://image.tmdb.org/t/p/w500/X0D88gIv47L4kpdvSvF1NsLPtL.jpg",
    "overview": "기억할 수도, 기억하기도 싫었던 그 때의 제주가 내 아들에게 찾아왔다. 촌스러운 이름이 인생 최대 고민인 영옥. 어쩌다 서울서 전학 온 경태의 눈에 들어, 절친 민수를 밀어내고 난생처음 반장이 된다. 하지만 자리가 무색하게, 경태의 꼭두각시가 되어 교실 안 폭력을 방관한다. 지독하게 아픈 봄이었수다, 우리 어멍의 1949년은. 손자뻘 아들 영옥을 홀로 키워온 정순. 서울서 새로 온 의사와 함께, 까맣게 지워진 어린 시절의 기억을 되찾아보려 한다. 분홍색 선글라스를 쓰고 하얀 차를 몰고 제주 곳곳을 누빌수록, 50년 전 그날의 숨겨진 약속이 떠오르는데…"
  },
  {
    "movieCd": "20247490",
    "movieNm": "누룩",
    "openDt": "2026-04-15",
    "genreNm": "드라마,미스터리",
    "nationAlt": "한국",
    "director": "장동윤",
    "isReRelease": false,
    "posterUrl": "https://image.tmdb.org/t/p/w500/hOzXWBsGMMHlXuBUGALVXBjTvP.jpg",
    "overview": "동네 사람들만 아는 소문난 양조장 집 딸이자 막걸리를 사랑하는 열 여덟 소녀 ‘다슬’은 어느 날 막걸리의 맛이 변한 걸 느끼고 막걸리의 주재료인 사라진 누룩을 찾아 나서며 벌어지는 특별한 이야기"
  },
  {
    "movieCd": "20262204",
    "movieNm": "류이치 사카모토: 도쿄 멜로디 ",
    "openDt": "2026-04-15",
    "genreNm": "다큐멘터리,음악",
    "nationAlt": "프랑스",
    "director": "엘리자베스 레나드",
    "isReRelease": false,
    "posterUrl": "https://image.tmdb.org/t/p/w500/nlXp3K6rIP34IavABLSSfbCWQDb.jpg",
    "overview": "일렉트로닉 밴드 ‘옐로우 매직 오케스트라’와 영화 ‘전장의 크리스마스’ 주제곡 ‘Merry Christmas Mr. Lawrence’로 세계적인 성공을 거둔 류이치 사카모토는 1984년 자신의 새로운 솔로 앨범 ‘음악도감’ 작업을 하고 있다."
  },
  {
    "movieCd": "20250411",
    "movieNm": "미야자키 하야오의 그대들은 어떻게 살 것인가",
    "openDt": "2026-04-15",
    "genreNm": "다큐멘터리",
    "nationAlt": "일본",
    "director": "Kaku Arakawa",
    "isReRelease": false,
    "posterUrl": "https://image.tmdb.org/t/p/w500/pgr6EXnzKNtPikxBj5qS7tS8N3M.jpg",
    "overview": "아카데미상을 수상한 <그대들은 어떻게 살 것인가>. 인생이 담긴 마지막 작품을 완성하기 위한 미야자키 하야오의 고뇌와 갈등, 긴 세월을 함께한 동료들과 예기치 못한 이별까지…"
  },
  {
    "movieCd": "20262541",
    "movieNm": "빨간 나라를 보았니",
    "openDt": "2026-04-15",
    "genreNm": "다큐멘터리",
    "nationAlt": "한국",
    "director": "홍영아",
    "isReRelease": false,
    "posterUrl": "https://image.tmdb.org/t/p/w500/pYpRfxcuUkXFTvSPuNlPSQI0QZ8.jpg",
    "overview": "2022년 윤석열 대통령이 당선된 이후 치러진 전국지방동시선거! 민주당 험지인 경북에서는 국민의 힘 이철우 지사의 무투표 당선이 이야기되고 있었다. 그러나 이에 맞서 모두가 출마를 말리는 선거에 뛰어든 임미애 후보! 그리고 예상 밖의 선전! 그녀의 득표율은 이재명 후보 득표율을 넘어설 수 있을까... 2024년 국회의원 선거. 빨간 나라 경북의 지는 선거에 또 뛰어드는 파란 후보들! 윤석열 심판과 채상병 특검이 뒤흔든 분위기는 민주당에 유리하지만, 경북도 그럴까? 이번에는 다를 것 같은 기분이 든다. 이 판을 뒤집을 수 있을까..."
  },
  {
    "movieCd": "manual_20260415_shapeofwater",
    "movieNm": "셰이프 오브 워터",
    "openDt": "2026-04-15",
    "genreNm": "판타지",
    "nationAlt": "미국",
    "director": "기예르모 델 토로",
    "isReRelease": true,
    "overview": ""
  },
  {
    "movieCd": "20262383",
    "movieNm": "쉘터",
    "openDt": "2026-04-15",
    "genreNm": "액션,범죄,스릴러",
    "nationAlt": "미국",
    "director": "릭 로먼 워",
    "isReRelease": false,
    "posterUrl": "https://image.tmdb.org/t/p/w500/tS3UZlVfESO4z8inIZXGiHNgDfE.jpg",
    "overview": "등대에 홀로 숨어살던 한 남자. 그 앞에 홀로 나타난 한 소녀. 이제 소녀를 지키기 위해, 그 남자의 숨겨왔던 액션 본능이 깨어난다!"
  },
  {
    "movieCd": "20250586",
    "movieNm": "주희에게",
    "openDt": "2026-04-15",
    "genreNm": "다큐멘터리",
    "nationAlt": "한국",
    "director": "Jang Ju-hee,Bu Seong-pil,Kim Sung-hwan",
    "isReRelease": false,
    "posterUrl": "https://image.tmdb.org/t/p/w500/rdk36mKEqkhmN64U0ZPBMb1hohE.jpg",
    "overview": "세상의 속도대로 갈수 없는 철규. 그리고 아직도 해결되지 않은 과거로 현재를 사는 인숙. 그리고 그 두 사람으로 인해 다큐멘터리 감독으로 살아가게 된 성필. 이 세 사람의 삶은 암을 경험 했던 이십대의 주희에게, 그리고 가정폭력 피해자에서 현재는 활동가가 된 주희에게, 영화가 늘 실패의 경험이었던 주희에게 삶의 동기가 되었다. 자신의 의존해야 할 부양자로부터 겪은 폭력과 신체적 고통 속에서 생존하기 위해 자신의 삶을 타인의 것처럼 방관했던 주희는 결국엔 이 영화의 연출로써 이야기를 써내려가는 주체로, 그리고 세 사람들과 연결되며 자기 자신으로 살아가는 것이 무엇인지 찾아가게 된다."
  },
  {
    "movieCd": "20262202",
    "movieNm": "침묵의 친구",
    "openDt": "2026-04-15",
    "genreNm": "드라마",
    "nationAlt": "독일",
    "director": "Ildikó Enyedi",
    "isReRelease": false,
    "posterUrl": "https://image.tmdb.org/t/p/w500/5YxIvLizm9MisC4kRJo4ElPmsLl.jpg",
    "overview": "독일 대학의 한 식물원에는 1832년부터 인간을 바라보며 뿌리내린 장엄한 한 그루의 은행나무가 서있다. 1908년 대학 최초의 여학생. 1972년 식물과 사랑을 동시에 키우는 청년. 2020년 고독한 신경과학자. 한 세기가 넘는 시간 동안 이 은행나무는 세 사람들의 삶 속으로 고요히 가지를 뻗어 하나로 연결되기 시작한다."
  },
  {
    "movieCd": "20262441",
    "movieNm": "퀸 락 몬트리올",
    "openDt": "2026-04-15",
    "genreNm": "음악,다큐멘터리",
    "nationAlt": "영국",
    "director": "사울 스위머",
    "isReRelease": false,
    "posterUrl": "https://image.tmdb.org/t/p/w500/ynnYU19czD7gizvQMRMsTeKqcBM.jpg",
    "overview": "'보헤미안 랩소디'부터 '위 윌 락 유', '위 아더 챔피온스'까지, 1981년 11월, 캐나다 몬트리올을 열광시킨 퀸의 전설적인 라이브가 스크린에서 부활한다."
  },
  {
    "movieCd": "manual_20260415_trumanshow",
    "movieNm": "트루먼 쇼",
    "openDt": "2026-04-15",
    "genreNm": "드라마",
    "nationAlt": "미국",
    "director": "피터 위어",
    "isReRelease": true,
    "posterUrl": "https://image.tmdb.org/t/p/w500/AsUv4pFf1UQuOLKf7nYUXgmgCNf.jpg",
    "overview": "트루먼 버뱅크는 작고 조용한 섬마을에 사는 평범한 세일즈맨이다. 그런 그가 자신의 삶에 대해 의문을 갖기 시작한 것은 평소와 다름없이 평범한 어느 날, 갑자기 하늘에서 촬영용 조명등이 떨어지고, 어렸을 적 자신이 익사를 직접 목격했던 아버지가 살아오고, 또 누군가에 의해 끌려가는 등 상식 밖의 일들이 벌어지고 나서부터였다. 평생을 그다지 신경쓰지 않고 지냈던 일상이었지만 주변을 보니 이상한 일이 너무 많았다. 결국 자신이 특별한 상황에 놓여있다는 확신을 하게된 트루먼은 첫사랑 실비아의 모든 것이 다 거짓라는 말을 되새기며 일상으로부터 탈출을 결심하게 되는데..."
  },
  {
    "movieCd": "20259339",
    "movieNm": "힌드의 목소리",
    "openDt": "2026-04-15",
    "genreNm": "드라마,역사",
    "nationAlt": "프랑스",
    "director": "Kaouther Ben Hania",
    "isReRelease": false,
    "posterUrl": "https://image.tmdb.org/t/p/w500/rHYvGIEBHnAzkQsg1xiX5MJy7td.jpg",
    "overview": "2024년 1월 29일, 가자지구에 대피 명령이 떨어진 날. 6살 소녀로부터 1통의 신고가 접수된다. “나한테 총을 쏘고 있어요, 제발 데리러 와 주세요” 적신월사는 구조대와 단 8분 거리에 있는 ‘힌드’를 구하기 위해 조정 절차를 이어가지만 구조 작전은 무려 5시간 동안 이어지는데..."
  },
  {
    "movieCd": "20262811",
    "movieNm": "극장판 총집편 걸즈 밴드 크라이 있잖아, 미래.",
    "openDt": "2026-04-16",
    "genreNm": "애니메이션,드라마,코미디,음악",
    "nationAlt": "일본",
    "director": "사카이 카즈오",
    "isReRelease": false,
    "posterUrl": "https://image.tmdb.org/t/p/w500/muigQVrx1QjkmjDQxYmI32Yd0HG.jpg",
    "overview": "토게나시 토게아리를 결성한 니나는 버려 두었던 고향과 마주한다. 모모카는 버려 두었던 밴드인 '다이아몬드 더스트'와 마주한다. 각자의 과거를 극복한 두 사람에게 자극받아 과거를 넘어서 프로 데뷔를 목표로 했지만, 사회의 논리에 적응하지 못해 프로를 그만두고 인디 밴드로서 살아가기로 결심한다."
  },
  {
    "movieCd": "20262907",
    "movieNm": "고트: 더 레전드",
    "openDt": "2026-04-17",
    "genreNm": "애니메이션,코미디,가족",
    "nationAlt": "미국",
    "director": "Tyree Dillihay",
    "isReRelease": false,
    "posterUrl": "https://image.tmdb.org/t/p/w500/otP94vckeMXAgQxzhcRkZSeSmYv.jpg",
    "overview": "큰 꿈을 품은 작은 염소 윌은 세계에서 가장 빠르고 사나운 동물들이 지배하는 고강도 혼성 풀컨택트 스포츠 ‘로어볼’의 프로 리그에 합류할 단 한 번의 기회를 얻게 된다. 새 팀의 동료들은 작은 염소가 팀 명단에 오른 것을 탐탁지 않게 여기지만, 윌은 ‘작아도 충분히 해낼 수 있다’는 것을 증명하고 스포츠의 판도를 바꾸겠다는 굳은 결의를 다진다. 이를 위해 그는 지금까지 한 번도 해본 적 없는 도전에 나서야 한다."
  },
  {
    "movieCd": "20242463",
    "movieNm": "나를 용서해 아침마다 모텔로 출근한 내 아내",
    "openDt": "2026-04-17",
    "genreNm": "",
    "nationAlt": "일본",
    "director": "정보 없음",
    "isReRelease": false,
    "overview": ""
  },
  {
    "movieCd": "20262639",
    "movieNm": "노멀",
    "openDt": "2026-04-17",
    "genreNm": "액션,범죄,스릴러",
    "nationAlt": "미국",
    "director": "벤 휘틀리",
    "isReRelease": false,
    "posterUrl": "https://image.tmdb.org/t/p/w500/A7TN0R78eenIf7hED3k96POTJMX.jpg",
    "overview": "눈 덮인, 조용하고 평범한 마을 노멀. 보안관 건더슨의 갑작스러운 죽음으로 공석이 된 자리에, 율리시스가 임시 보안관으로 부임한다. 조용한 마을, 친절한 이웃, 평화로운 하루. 율리시스의 목표는 단 하나, 이 마을을 처음 왔을 때 모습 그대로 두고 돌아가는 것. 그러던 어느 날, 단조로운 마을에 느닷없이 벌어진 은행 강도 사건. 현장을 제압하기 위해 출동한 율리시스는 뜻밖에도 동료들에게 포위당하게 되고, 그 순간, 평범해 보이던 노멀 마을에 숨겨진 거대한 비밀이 서서히 모습을 드러내기 시작한다."
  },
  {
    "movieCd": "20263090",
    "movieNm": "붉은 10월의 반란 파트 2",
    "openDt": "2026-04-17",
    "genreNm": "",
    "nationAlt": "기타",
    "director": "정보 없음",
    "isReRelease": false,
    "overview": ""
  },
  {
    "movieCd": "20242482",
    "movieNm": "관념의 남자 김철수",
    "openDt": "2026-04-22",
    "genreNm": "코미디,드라마",
    "nationAlt": "한국",
    "director": "이재리",
    "isReRelease": false,
    "posterUrl": "https://image.tmdb.org/t/p/w500/tz5HaFF9pHlwVMIKlCvnKeIonaa.jpg",
    "overview": "늘 정답 같은 선택만 해오며 교과서처럼 살아온 초등학교 교사 ‘철수’. 같은 학교 동료 교사이자 여자친구인 ‘세미’에게 프로포즈를 하지만, 세미는 확신 없는 말만 남긴 채 산티아고로 떠나버린다. 그녀와 다시 만나기 위해 여러 방법을 찾아 나선 철수는 정신과 의사 ‘김레오나르도’를 만나고, 재회를 위해서는 극단적인 변화가 필요하다는 처방을 받는다. 결국 철수는 극단적인 변화를 위해 ‘위성 도시’로 향하고, 그곳에서 어릴 적 친구 영희를 우연히 만나게 되는데..."
  },
  {
    "movieCd": "20262775",
    "movieNm": "기동전사 건담: 섬광의 하사웨이 키르케의 마녀",
    "openDt": "2026-04-22",
    "genreNm": "애니메이션,SF,전쟁,드라마",
    "nationAlt": "일본",
    "director": "무라세 슈코",
    "isReRelease": false,
    "posterUrl": "https://image.tmdb.org/t/p/w500/tCtECshR8McDJRlHxrN85A7urXD.jpg",
    "overview": "‘샤아의 반란’이라 불린 제2차 네오지온 항쟁이 끝난 후 12년. 우주세기 105년. 지구 환경은 계속해서 악화되고, 지구연방정부는 지구를 보존한다는 명목 아래 민간인을 강제로 우주로 이주시키는 ‘인간 사냥’ 정책까지 자행하며 부패의 극에 달한다. 이러한 현실에 맞서 고위 관료 암살을 통해 저항을 시작한 반정부 조직 ‘마프티’. ‘샤아의 환생’이라 불리며 조직을 이끄는 리더 마프티 나비유 에린의 정체는, 과거 브라이트 노아의 아들이자 전쟁을 겪은 청년 하사웨이 노아였다. 신비한 힘을 지닌 소녀 기기 안달루시아를 만난 이후, 하사웨이는 잊고 있던 과거와 마주하며 깊은 혼란에 빠진다. 그럼에도 그는 ‘마프티’의 이상을 위해 지구연방 고위 관료들이 집결하는 애들레이드 회의 습격 작전을 준비한다. 한편, 지구연방군의 젊은 지휘관 케네스 슬렉 대령 역시 애들레이드 회의를 방어하는 동시에 ‘마프티’의 섬멸을 목표로 움직이기 시작한다. 기기 또한 자신에게 주어진 신비한 운명에 이끌리듯 홍콩으로 향한다. 애들레이드 회의를 앞두고, 에어즈록을 무대로 서로 다른 신념이 충돌하는 운명의 결전이 시작된다. 과연, ‘마프티’와 ‘키르케 부대’ 중 행운의 여신은 누구의 편에 설 것인가."
  },
  {
    "movieCd": "20263141",
    "movieNm": "돌핀 팬츠 입고 유혹하는 옆집녀",
    "openDt": "2026-04-22",
    "genreNm": "",
    "nationAlt": "한국",
    "director": "정보 없음",
    "isReRelease": false,
    "overview": ""
  },
  {
    "movieCd": "20262685",
    "movieNm": "란 12.3",
    "openDt": "2026-04-22",
    "genreNm": "다큐멘터리",
    "nationAlt": "한국",
    "director": "이명세",
    "isReRelease": false,
    "posterUrl": "https://image.tmdb.org/t/p/w500/wU6UC10xiUSEfdlT0U1OZJqMa0A.jpg",
    "overview": "2024년 12월 3일 밤, 윤석열 대통령의 기습적인 비상계엄 선포로 평화로웠던 일상이 깨졌다. 다시 반복된 과거의 그날처럼, 무장한 군 병력은 헌법 기관을 무력화하려 하고 계엄에 반대하여 민주주의를 지키려는 시민과 국회의원들은 국회로 몰려간다. 분초를 다투는 상황 속, 이들의 숨 막히는 싸움이 벌어지는데…"
  },
  {
    "movieCd": "20262776",
    "movieNm": "르누아르",
    "openDt": "2026-04-22",
    "genreNm": "드라마",
    "nationAlt": "일본,프랑스",
    "director": "하야카와 치에",
    "isReRelease": false,
    "posterUrl": "https://image.tmdb.org/t/p/w500/jEZ7ezDPnGElqk3Yomked5aOE6P.jpg",
    "overview": "11살 ‘후키’가 세상을 알고 쑥쑥 자라나는 1980년 어느 여름 방학의 이야기를 담은 2026년 봄, 언젠가 아이였고 어른이 된 우리에게 왠지 반가운 <르누아르>"
  },
  {
    "movieCd": "20262657",
    "movieNm": "리 크로닌의 미이라",
    "openDt": "2026-04-22",
    "genreNm": "공포,미스터리",
    "nationAlt": "미국",
    "director": "리 크로닌",
    "isReRelease": false,
    "posterUrl": "https://image.tmdb.org/t/p/w500/zXlwtzXP80yc3X0VokdxvmsFQfw.jpg",
    "overview": "한 기자의 어린 딸이 흔적도 없이 사막으로 사라진다. 그리고 8년 후, 산산이 부서진 가족은 그녀가 다시 돌아왔다는 소식에 충격을 받는다. 하지만 기쁨으로 가득해야 할 재회는 곧 살아 있는 악몽으로 변해간다."
  },
  {
    "movieCd": "20257301",
    "movieNm": "마지막 야구 경기",
    "openDt": "2026-04-22",
    "genreNm": "드라마,코미디",
    "nationAlt": "미국",
    "director": "카슨 룬드",
    "isReRelease": false,
    "posterUrl": "https://image.tmdb.org/t/p/w500/2NydzK2umgHwDgvFwGxCLmSBeji.jpg",
    "overview": "한 무리의 성인 남자들이 그들이 사랑하는 야구장이 철거되기 하루 전날 연장전까지 이어지는 취미 야구 경기를 펼친다. 유머와 향수가 뒤섞이는 가운데 해가 지고, 한 시대의 끝이 도래한다."
  },
  {
    "movieCd": "20244564",
    "movieNm": "새벽의 Tango",
    "openDt": "2026-04-22",
    "genreNm": "드라마",
    "nationAlt": "한국",
    "director": "김효은",
    "isReRelease": false,
    "posterUrl": "https://image.tmdb.org/t/p/w500/pSPv9MaIHHV5RkZNcvvJxOFDMiy.jpg",
    "overview": "믿었던 친구의 배신으로 깊은 상처를 입은 '지원'. 세상으로부터 도망치듯 들어간 공장에서 누구보다 긍정과 다정함의 힘을 믿는 룸메이트 '주희'를 만나는데, 갑자기 'Tango'를 함께 추자는 제안이 부담스럽기만 하다. 하지만 '지원'은 자신을 기다리며 건네는 '주희'의 서툰 스텝을 따라가며 굳게 닫았던 마음의 문을 용기 내어 조금씩 열기 시작한다. 마침내 다시 누군가를 믿어보려던 찰나, 어린 조장 '한별'이 일으킨 사고에 '주희'와 함께 휘말린 '지원'의 일상은 흔들리기 시작하는데…"
  },
  {
    "movieCd": "20262787",
    "movieNm": "원 오크 록 디톡스 투어 인 시네마",
    "openDt": "2026-04-22",
    "genreNm": "음악,다큐멘터리",
    "nationAlt": "한국",
    "director": "Naoto Amazutsumi",
    "isReRelease": false,
    "posterUrl": "https://image.tmdb.org/t/p/w500/AqlcUdVgXywN2kQFtHDY6kZmGyk.jpg",
    "overview": "<원 오크 록 디톡스 투어 인 시네마>는 2025년 일본 가나가와 닛산 스타디움에서 열린 원 오크 록의 레전드 공연을 담은 콘서트 영화다. 약 3년 만에 발표한 정규 앨범 ‘DETOX’는 보다 강렬하고 직선적인 록 사운드로 밴드의 새로운 챕터를 열었다. 이를 중심으로 진행된 ‘DETOX WORLD TOUR’는 북미와 유럽, 아시아를 거치며 이어졌고 그 여정의 정점이 바로 닛산 스타디움 공연이었다. 2005년 작은 라이브하우스에서 시작한 원 오크 록은 지금까지 일본을 넘어 전 세계 무대에서 활동하며 글로벌 팬덤을 구축해 왔다. 타카의 폭발적인 보컬과 밴드의 강렬한 연주, 그리고 공연장을 가득 채운 관객의 함성은 그들이 걸어온 시간과 현재의 에너지를 고스란히 보여준다. 이 영화는 그날 밤 공연의 열기와 감정을 스크린에 담아낸다. 무대 위의 치열한 퍼포먼스와 순간순간 터져 나오는 관객의 반응, 그리고 밴드와 팬이 하나가 되는 공연의 순간들이 이어진다. SCREENX와 4DX 포맷으로 상영되는 이번 작품은 스타디움 공연의 스케일과 현장의 열기를 극장 공간으로 확장시켜 관객이 공연의 중심에 서 있는 듯한 몰입감을 선사한다."
  },
  {
    "movieCd": "20240532",
    "movieNm": "짱구",
    "openDt": "2026-04-22",
    "genreNm": "코미디,드라마",
    "nationAlt": "한국",
    "director": "정우",
    "isReRelease": false,
    "posterUrl": "https://image.tmdb.org/t/p/w500/8ddOwCQnSHwtVIvuo4IiyCcPeOW.jpg",
    "overview": "배우가 되고 싶어 서울 자취러가 된 부산 사나이 짱구. 전기세도 못 낼 만큼 팍팍한 서울살이 속에서 되는 일은 좀처럼 없다. 대사는 꼬이고, 서울말은 더 꼬이고, 연애도 밀당에 밀린다. 하지만 짱구는 넘어지면 털고 일어나고 쪽팔리면 더 크게 웃는다. 인생이 뜻대로 안 풀릴 때 이렇게 버티는 방법도 있다. 무겁지 않다. 그렇다고 가볍지도 않다. 웃기면서 뜨겁다."
  },
  {
    "movieCd": "20263121",
    "movieNm": "플래닛 어스 : 대자연의 힘 ",
    "openDt": "2026-04-22",
    "genreNm": "",
    "nationAlt": "영국",
    "director": "정보 없음",
    "isReRelease": false,
    "overview": ""
  },
  {
    "movieCd": "20228063",
    "movieNm": "미스매치",
    "openDt": "2026-04-23",
    "genreNm": "코미디,드라마",
    "nationAlt": "한국",
    "director": "손태웅",
    "isReRelease": false,
    "posterUrl": "https://image.tmdb.org/t/p/w500/jccJeAT7ZvO2kYMtT2f9mDVVE3R.jpg",
    "overview": "“내가 책임질게 됐지?” 매번 큰소리만 뻥뻥! 사업 실패, 직장 해고까지 무능력한 가장 봉수 회사에서도 집안에서도 기를 펴지 못하고 살아가던 어느 날! 불의의 사고를 겪게 되는데… 몸은 멀쩡한데… 머릿속은 백지장?! “여긴 어디? 난, 누구?” 어제의 나도, 가족의 얼굴도 모두 새로 시작하게 된 봉수의 인생 리부트! 과연 봉수는 잃어버린 기억을 되찾고 가족의 재결합을 할 수 있을까?"
  },
  {
    "movieCd": "20263123",
    "movieNm": "엉덩이 큰 여선생의 유혹 ",
    "openDt": "2026-04-23",
    "genreNm": "",
    "nationAlt": "한국",
    "director": "정보 없음",
    "isReRelease": false,
    "overview": ""
  },
  {
    "movieCd": "20263124",
    "movieNm": "여친 몰래 빨아준 옆집여자",
    "openDt": "2026-04-23",
    "genreNm": "",
    "nationAlt": "한국",
    "director": "정보 없음",
    "isReRelease": false,
    "overview": ""
  },
  {
    "movieCd": "20261446",
    "movieNm": "오시리스",
    "openDt": "2026-04-23",
    "genreNm": "SF,액션,공포",
    "nationAlt": "미국",
    "director": "윌리엄 카우프먼",
    "isReRelease": false,
    "overview": "미군 특공대원들이 작전 도중 정체 불명의 우주선에 납치된다. 거대 금속 구조물과 기계음으로 가득한 밀폐된 외계 우주선 내부에서 깨어난 그들은 인간을 식량으로 삼는 외계 종족의 먹잇감이 된다. 위험한 새로운 환경에서 특공대원들은 오랜 기간 외계 종족을 피해 살아남은 ‘안야’가 이끄는 생존자 그룹과 협력해 탈출을 시도하지만 그 과정에서 팀원들이 하나둘 희생된다.",
    "posterUrl": "https://image.tmdb.org/t/p/w500/awGTMnXYtaobuQV8ROyRmjiDuMa.jpg"
  },
  {
    "movieCd": "20259601",
    "movieNm": "달걀 원정대",
    "openDt": "2026-04-29",
    "genreNm": "판타지,모험,코미디",
    "nationAlt": "미국",
    "director": "Weston Razooli",
    "isReRelease": false,
    "overview": "동네의 소문난 꼬마 악동들 ‘앨리스, 헤이즐, 조디’. 고대하던 비디오 게임을 드디어 손에 넣지만, 굳게 잠긴 TV 화면 앞에서 좌절한다. 암호를 알아낼 방법은 단 하나, 엄마를 위한 맛있는 블루베리 파이를 구해올 것! 파이 품절 대란 속에서 아이들은 직접 베이킹에 나서지만 가장 중요한 재료인 달걀마저 정체불명의 남자에게 도둑맞고 만다. 달걀을 되찾기 위해 미지의 숲으로 뛰어든 셋은 수상한 마녀와 신비로운 소녀를 마주하며 예상치 못한 사건에 휘말리게 되는데...",
    "posterUrl": "https://image.tmdb.org/t/p/w500/etQH4l7DRmd4sdVibgJIfpQaRqz.jpg"
  },
  {
    "movieCd": "manual_20260429_vivaldiandme",
    "movieNm": "비발디와 나",
    "openDt": "2026-04-29",
    "genreNm": "드라마,음악",
    "nationAlt": "이탈리아",
    "director": "다미아노 미키엘레토",
    "isReRelease": false,
    "overview": "18세기 초 베네치아, 뛰어난 오케스트라로 명성 높은 피에타 고아원. 화려한 명성과 달리 소녀들은 얼굴도 이름도 숨긴 채 연주해야 하고, 세상 밖으로 나갈 수 있는 유일한 방법은 결혼뿐이다. 스무 살의 천재 바이올리니스트 체칠리아는 새로 부임한 음악 교사 비발디를 만나며 그의 음악을 통해 자신의 재능과 운명을 마주하게 된다.",
    "posterUrl": "https://image.tmdb.org/t/p/w500/40DCL4scy4pxAodQomVhuxRizXr.jpg"
  },
  {
    "movieCd": "20263207",
    "movieNm": "사토상과 사토상",
    "openDt": "2026-04-29",
    "genreNm": "드라마,로맨스",
    "nationAlt": "일본",
    "director": "Chihiro Amano",
    "isReRelease": false,
    "overview": "“나도 타모츠랑 같이 공부해 볼까봐” 직장인. 대학 동기인 사토 타모츠와 연애 동거 중인 그 여자, 사토 사치. “사치, 너 진심으로 변호사가 되려고?” 아르바이트 및 사법시험 N수생 그 남자, 사토 타모츠. 사치는 타모츠의 거듭되는 시험을 응원하기 위해 처음으로 사법시험에 도전한다. 그리고 결과 발표 당일, “있다! … 사치 번호만…”",
    "posterUrl": "https://image.tmdb.org/t/p/w500/dAKpAAODOpfB0RpmPy4cxc9DosP.jpg"
  },
  {
    "movieCd": "20259773",
    "movieNm": "슈퍼 마리오 갤럭시",
    "openDt": "2026-04-29",
    "genreNm": "가족,코미디,모험,판타지,애니메이션",
    "nationAlt": "미국",
    "director": "아론 호바스",
    "isReRelease": false,
    "posterUrl": "https://image.tmdb.org/t/p/w500/knaXOBDBecVBWZVup3zXaOoy23v.jpg",
    "overview": "브루클린의 배관공에서 세계를 구한 히어로로 레벨업한 형제 ‘마리오’와 ‘루이지’는 모래 왕국에서 임무를 수행하던 중, 길을 잃은 ‘요시’를 구출하며 특별한 우정을 쌓게 된다. 한편, 무너진 ‘쿠파’ 가문의 명예를 되찾기 위해 악의 왕자 ‘쿠파주니어’는 은하계의 수호자이자 치코들의 엄마 ‘로젤리나’를 납치하고, 버섯 왕국에 잡힌 아빠 ‘쿠파’를 되찾기 위해 왕국을 습격한다. 다시 찾아온 위기 속에서 마리오와 루이지, 피치, 키노피오 그리고 새로 합류한 요시까지 로젤리나도 구하고, 쿠파주니어의 비범한 계획을 막기 위해 넓은 갤럭시로 뛰어들게 되는데…"
  },
  {
    "movieCd": "manual_20260429_devilwearsprada2",
    "movieNm": "악마는 프라다를 입는다 2",
    "openDt": "2026-04-29",
    "genreNm": "코미디,드라마",
    "nationAlt": "미국",
    "director": "데이비드 프랭클",
    "isReRelease": false,
    "posterUrl": "https://image.tmdb.org/t/p/w500/28A1VUDML1RzENYNtIU1WkBLT9V.jpg",
    "overview": "전 세계 트렌드를 주도해 온 전설적인 패션 매거진 ‘런웨이’가 급변하는 미디어 시장 속에서 예기치 못한 위기에 직면한다. ‘런웨이’를 지켜내려는 편집장 ‘미란다’와 20년 만에 신임 기획 에디터로 당당히 돌아온 ‘앤디’, 그리고 이제는 럭셔리 브랜드 임원이 되어 다시 나타난 ‘에밀리’까지 더 화려하고, 치열해진 뉴욕 패션계에서 주도권을 차지하기 위해 벌이는 이들의 새로운 이야기가 펼쳐진다!"
  },
  {
    "movieCd": "20262116",
    "movieNm": "피카소. 파리에서의 반란",
    "openDt": "2026-04-29",
    "genreNm": "다큐멘터리",
    "nationAlt": "이탈리아",
    "director": "Simona Risi",
    "isReRelease": false,
    "posterUrl": "https://image.tmdb.org/t/p/w500/dbIMAvBOgnKBPWRSZsj2sIshc93.jpg",
    "overview": "예술가, 남자, 연인, 무정부주의자, 이방인, 혁명가... 파블로 피카소 서거 50주년을 기념해 만든 이 특집 다큐멘터리는 이 20세기의 가장 놀라운 예술가에 대한 새로운 해석을 제공한다. 종종 가면 뒤에 숨겨져 일반인들이 알지 못하는 피카소의 모순적 성격, 그의 관대함과 전제주의, 그의 햇살과 그림자, 그리고, 모순, 관용, 외국인 혐오로 가득 찬 그의 시대의 역설적인 파리를 배경으로 이 예술가의 이중적 성격을 탐구한다."
  },
  {
    "movieCd": "20262906",
    "movieNm": "극장판 반짝반짝 달님이: 싱어롱 파티",
    "openDt": "2026-05-01",
    "genreNm": "애니메이션,가족,판타지,모험,음악",
    "nationAlt": "한국",
    "director": "이병직",
    "isReRelease": false,
    "posterUrl": "https://image.tmdb.org/t/p/w500/vKS6arCPL0rMLeUgH1W4CE2TfUJ.jpg",
    "overview": "상상력 가득한 6살 공감소녀 달님이의 환상 속 어드벤처! 동화책 속으로 들어가 백설공주를 만나고, 공룡 친구 ‘핑크’를 지키기 위해 공룡 세상으로 떠나고, 동생과 함께한 캠핑에서 가족의 소중함을 느끼는 달님이의 판타지 여행! 상상이 현실이 되는 세 가지 이야기 속에서 친구와 가족, 그리고 사랑의 마음을 배워 가는 달님이에게 이번엔 어떤 놀라운 모험이 펼쳐질까? 노래하고 춤추며 모두 함께 즐기는 신나는 싱어롱 파티가 시작된다!"
  },
  {
    "movieCd": "20263327",
    "movieNm": "사랑의 하츄핑 특별판",
    "openDt": "2026-05-01",
    "genreNm": "",
    "nationAlt": "한국",
    "director": "김수훈",
    "isReRelease": false,
    "overview": ""
  },
  {
    "movieCd": "20263146",
    "movieNm": "캣 앤 독",
    "openDt": "2026-05-04",
    "genreNm": "모험,코미디",
    "nationAlt": "프랑스",
    "director": "림 케리시",
    "isReRelease": false,
    "overview": "도둑 잭은 박물관에서 루비를 훔쳐서 나오던 중 마주친 경찰과 몸싸움을 벌이다가 그만 루비를 놓치게 된다. 그 순간 떠돌이 개 쉬쉬가 루비를 삼키게 되고 삼킨 루비를 찾기 위해 도둑 잭은 떠돌이 개 쉬쉬와 함께 비행기에 타려 한다. 잭은 빠른 수속을 위해 시각 장애인인 척하다가 모니카와 고양이 디바를 마주친다. 화물칸으로 이송 중이던 쉬쉬와 디바는 철장을 빠져나오면서 주인들을 잃게 되는데...",
    "posterUrl": "https://image.tmdb.org/t/p/w500/jeRwrMXgOF2o3GqzIoYNSZ5W1yv.jpg"
  },
  {
    "movieCd": "20261243",
    "movieNm": "그녀가 돌아온 날",
    "openDt": "2026-05-06",
    "genreNm": "드라마",
    "nationAlt": "한국",
    "director": "홍상수",
    "isReRelease": false,
    "posterUrl": "https://image.tmdb.org/t/p/w500/pzAR32SOHwYT9OebuPh7jiSWapf.jpg",
    "overview": "결혼 후 연기를 안 하게 되었고, 이혼 후 다시 일을 하기 위해 독립영화를 한 편 찍었다. 오늘 그 찍은 영화의 개봉을 위해 인터뷰를 한다. 중년의 나이가 돼서 아주 오랜만에 세상에 배우로 얼굴을 내미는 날이다. 세 번의 인터뷰가 삼 십분 간격으로 이어지고 여자는 질문들에 최선을 다해서 답한다. 인터뷰 후에 새로 시작한 연기수업에 가게 된다. 거기서 연기 선생은 오늘 있은 인터뷰를 다시 재현해보라고 한다. 인터뷰 중에 가장 중요한 부분에 다다르면 여자는 왠일인지 기억이 전혀 나지 않는 것 같다. 피곤하고 집으로 빨리 돌아가고 싶다. 딸이 기다리고 있다."
  },
  {
    "movieCd": "20262947",
    "movieNm": "모탈 컴뱃 2",
    "openDt": "2026-05-06",
    "genreNm": "액션,판타지,모험",
    "nationAlt": "미국",
    "director": "Simon McQuoid",
    "isReRelease": false,
    "posterUrl": "https://image.tmdb.org/t/p/w500/1NgBKiPrJzv1VHdEN8brdy59Rxo.jpg",
    "overview": "The fan favorite champions—now joined by Johnny Cage himself—are pitted against one another in the ultimate, no-holds barred, gory battle to defeat the dark rule of Shao Kahn that threatens the very existence of the Earthrealm and its defenders."
  },
  {
    "movieCd": "20250630",
    "movieNm": "빌리 아일리시 - 히트 미 하드 앤드 소프트: 더 투어",
    "openDt": "2026-05-06",
    "genreNm": "음악,다큐멘터리",
    "nationAlt": "미국",
    "director": "제임스 카메론",
    "isReRelease": false,
    "overview": "Captured during Billie Eilish's sold-out world tour, a concert experience from one of the most celebrated and successful artists of her generation, presented in immersive 3D.",
    "posterUrl": "https://image.tmdb.org/t/p/w500/c4WWethl0Jk60kB7ry1LrLmWuaQ.jpg"
  },
  {
    "movieCd": "20261943",
    "movieNm": "올 그린스",
    "openDt": "2026-05-06",
    "genreNm": "코미디,드라마",
    "nationAlt": "일본",
    "director": "Takashi Koyama",
    "isReRelease": false,
    "overview": "학교에서도, 집에서도 마음 붙일 곳 없는 보쿠 히데미. 예쁘고 쾌활하게 보이지만 말 못 할 사정을 가진 미루쿠. 꿈과 재능의 갈림길에서 좌절하는 이와쿠마코. 3인 3색 개성을 지닌 세 여고생, 초록으로 대동단결! 세 사람이 이루고자 하는 목표는 바로 이 답답한 시골 마을에서 탈출하기. 소녀들의 발칙하고 불미스러운 일확천금 계획이 시작된다.",
    "posterUrl": "https://image.tmdb.org/t/p/w500/xbSZGbv6yxY4onrbuTJZYEFnhhW.jpg"
  },
  {
    "movieCd": "20252801",
    "movieNm": "교생실습",
    "openDt": "2026-05-13",
    "genreNm": "공포,코미디",
    "nationAlt": "한국",
    "director": "김민하",
    "isReRelease": false,
    "posterUrl": "https://image.tmdb.org/t/p/w500/tDhDvACSDYPRbL86pQedoRXgxhJ.jpg",
    "overview": "엄청난 포부와 사명감을 안고 모교로 부임한 열혈 교생 은경. 어느 날, 은경은 기묘한 분위기의 교내 흑마술 동아리 쿠로이소라의 세 소녀 아오이, 리코, 하루카를 만나게 되고 모의고사 전국 1등을 놓치지 않는다는 이들의 비밀을 파헤치려 하는데..."
  },
  {
    "movieCd": "20259626",
    "movieNm": "마이클",
    "openDt": "2026-05-13",
    "genreNm": "음악,드라마",
    "nationAlt": "미국",
    "director": "안톤 후쿠아",
    "isReRelease": false,
    "posterUrl": "https://image.tmdb.org/t/p/w500/piMZqtd0gGS7OgkhDwiQ7vVViBQ.jpg",
    "overview": "어린 나이에 형제들과 ‘잭슨 파이브’ 그룹의 막내로 데뷔하자마자 음악적 천재성과 스타성으로 주목을 받은 ‘마이클 잭슨’. 전세계적인 스타로 성공하지만, 그는 가족에 대한 책임감과 자신의 음악적 정체성 사이에서 고민에 빠지게 된다."
  },
  {
    "movieCd": "20262921",
    "movieNm": "파티마가 사랑한 계절",
    "openDt": "2026-05-13",
    "genreNm": "드라마,로맨스",
    "nationAlt": "프랑스",
    "director": "합시아 헤지",
    "isReRelease": false,
    "posterUrl": "https://image.tmdb.org/t/p/w500/488QeW987DdK0RQGZISgBhuncn7.jpg",
    "overview": "운동을 좋아하는 17세 소녀 파티마. 어느 날 문득, 자신이 더 이상 남자친구에게 끌리지 않는다는 사실을 깨닫는다. 호기심 반, 두려움 반으로 레즈비언 데이팅 앱에 가입한 파티마는 한국계 여성 '지나'를 만나게 된다. 처음 느껴보는 감정 앞에서 그녀의 세계는 흔들리기 시작하고 사랑과 신앙 사이에서 파티마는 처음으로 자기 자신과 마주한다."
  },
  {
    "movieCd": "20261409",
    "movieNm": "피어스",
    "openDt": "2026-05-13",
    "genreNm": "드라마,미스터리,스릴러",
    "nationAlt": "싱가포르,대만,폴란드",
    "director": "Nelicia Low",
    "isReRelease": false,
    "posterUrl": "https://image.tmdb.org/t/p/w500/n0ms8DI33iLvf612zU1NTK9cjwI.jpg",
    "overview": "7년 전, 펜싱 경기 중 벌어진 살인 사건. 상대 선수를 살해한 혐의로 소년원에 수감됐던 형 ‘즈한’이 돌아온다. 세상 모두가 등을 돌린 가운데, 동생 ‘즈지에’는 유일하게 형의 결백을 믿고 곁을 지킨다. 형의 보살핌 속에 ‘즈지에’의 펜싱 실력은 빠르게 성장하지만, 형제라는 이름 아래 이어진 둘만의 시간은 점차 기묘한 의존과 집착으로 변해간다. 전국 선수권 대회를 앞둔 어느 날, 형의 서늘한 본성이 드러나며 굳게 믿어온 진실은 흔들리기 시작하는데…"
  },
  {
    "movieCd": "20247462",
    "movieNm": "훈련사",
    "openDt": "2026-05-13",
    "genreNm": "스릴러",
    "nationAlt": "한국",
    "director": "서은선",
    "isReRelease": false,
    "overview": "대중의 존경을 받는 완벽한 스타 반려견 훈련사 ‘하영’. 어느 날, 살인죄로 수감되었던 동생 ‘소라’가 불쑥 찾아오며 하영이 철저히 통제해 온 쇼윈도 일상에 균열이 생긴다. “사람답게 살고 싶어. 언니처럼” 설상가상, 하영의 팀원이 은폐한 유기견 ‘두부’가 사람을 공격하고, 어린 시절 화재 사건의 진실이 수면 위로 떠오르는데…",
    "posterUrl": "https://image.tmdb.org/t/p/w500/t6rvaBK4Dc7Vu1yUYQ9j1DNbdCa.jpg"
  },
  {
    "movieCd": "20262631",
    "movieNm": "5월18일생",
    "openDt": "2026-05-14",
    "genreNm": "드라마",
    "nationAlt": "한국",
    "director": "송동윤",
    "isReRelease": false,
    "overview": "1980년 5월 18일, 광주에서 태어난 소설가 ‘미수’의 삶은 이미 시작부터 비극이었다. 태어나던 날 행방불명된 아버지와 평생 그를 찾아다닌 어머니로 인한 외로움은 오직 글쓰기로 풀어낼 수 있었고, 세상과 단절한 채 작품 활동에만 전념하던 어느 날 요양원으로부터 ‘이서연’이라는 인물의 유품이 담긴 우편물을 받는다. 일기와 카세트테이프 속 기록과 기억의 파편을 조합해 그날의 진실을 마주하게 되는데…",
    "posterUrl": "https://image.tmdb.org/t/p/w500/qgoSpSiw9MqF8cpGG4mhUvQUF8O.jpg"
  },
  {
    "movieCd": "20263162",
    "movieNm": "그림자 내각",
    "openDt": "2026-05-14",
    "genreNm": "다큐멘터리",
    "nationAlt": "한국",
    "director": "Kim Si-woo",
    "isReRelease": false,
    "overview": "1979년 10월 16일, 유신정권을 종식한 부마 민주항쟁에서부터 시작하여 10.26 박정희 서거, 12.12 전두환의 군사반란, 2024년 12.3 윤석열의 내란으로 이어지는 대한민국의 과거부터 현재에 이르기까지 내란의 실체와 청산하지 못한 과거사를 추적하는 정치 다큐드라마로 군사반란과 내란을 어떻게 구조적으로 준비하였는지를 탐사한다. 그리고 전두환의 정적제거, 윤석열의 정적제거 실체를 추적하여 내란을 준비하는 과정을 낱낱이 파헤치고, 그 동조세력들의 실상을 추적한다. 또한 양극화의 뉴미디어와 국론분열 세력의 실체 및 독재권력으로 조성한 전두환, 노태우의 비자금 등을 집중 탐사하며, 전두환의 비자금이 내란 정권에 미친 영향과 과거 군사반란과 현재의 내란에 얽혀 있는 권력 주변의 검은 커넥션을 파헤친 작품이다.",
    "posterUrl": "https://image.tmdb.org/t/p/w500/1HXPRXq1app922weQgkkiYXGnFK.jpg"
  },
  {
    "movieCd": "20259727",
    "movieNm": "1026: 새로운 세상을 위한",
    "openDt": "2026-05-20",
    "genreNm": "다큐멘터리,드라마,역사",
    "nationAlt": "한국",
    "director": "최위안",
    "isReRelease": false,
    "posterUrl": "https://image.tmdb.org/t/p/w500/qd1zggtwHMu7wMCM9BzFLSidpJu.jpg",
    "overview": "숯과 얼음 같았던 두 사람이 어떤 해후를 하였을지는 알 길이 없다. 다만 김재규는 죽음 순간까지 의연함을 잃지 않았다. 재판 과정에서도 목숨을 구걸하지 않겠다며 변호인들의 변호를 거부했고 사형 직전 일체의 종교 의식도 거부한 채 오래전 어머니가 건네준 산복숭아씨 단주를 굴리며 쓸쓸히 홀로 형장의 이슬로 사라져 갔다. 오로지, 그가 남긴 마지막 말은 '대한민국 국민 여러분, 자유를 만끽하십시오’ 였다. 아무도 그를 알아주는 사람은 없었다."
  },
  {
    "movieCd": "20263344",
    "movieNm": "너바나 더 밴드 : 전설적 밴드 ‘너바나’와는 별 관련 없는 ‘너바나 더 밴드’의 콤비 맷과 제이. 어느 날 공연을 위해 타임머신을 만드는 황당한 작전을 세우고 처음 만났던 17년 전으로 돌",
    "openDt": "2026-05-20",
    "genreNm": "코미디,어드벤처,SF",
    "nationAlt": "캐나다",
    "director": "Matt Johnson",
    "isReRelease": false,
    "posterUrl": "https://image.tmdb.org/t/p/w500/sm5TGX8WbnCd9Uo26cLyTxVwA1n.jpg",
    "overview": "전설적 밴드 ‘너바나’와는 별로 관련이 없어 보이는 ‘너바나 더 밴드’의 콤비 맷과 제이. 어느 날 이들은 공연을 위해 타임 머신을 만들자는 황당한 계획을 세우고 처음 만났던 17년 전으로 돌아가기로 하는데…"
  },
  {
    "movieCd": "20248218",
    "movieNm": "반칙왕 몽키",
    "openDt": "2026-05-20",
    "genreNm": "다큐멘터리",
    "nationAlt": "한국",
    "director": "황다은",
    "isReRelease": false,
    "overview": "저출산 시대에 사남매는 반칙이다. 맞벌이도 모자랄 판에 외벌이는 반칙이다. 가부장제 남성 생계부양자 사회에서 전업주부 아빠는 반칙이다. 사교육 왕국에서 돈 안드는 사적인 교육은 반칙이다. 다둥이 자녀 양육도 벅찬데 마을 아이들까지 돌보는 것도 반칙이다. 페어플레이가 사라진 반칙 사회에서 살아남기 위한 10년 차 전업주부 아빠의 통쾌한 반칙 프로젝트가 펼쳐진다.",
    "posterUrl": "https://image.tmdb.org/t/p/w500/fQ6LKLzHqKQBjCX1AgW26fGmjL5.jpg"
  },
  {
    "movieCd": "20262975",
    "movieNm": "신극장판 은혼: 요시와라 대염상",
    "openDt": "2026-05-20",
    "genreNm": "애니메이션,액션,SF",
    "nationAlt": "일본",
    "director": "Naoya Ando",
    "isReRelease": false,
    "overview": "해결사 사무소를 운영하는 ‘사카타 긴토키’. 어느 날, 그는 소매치기로 생계를 이어가던 고아 소년 ‘세이타’를 만나게 된다. ‘세이타’의 소원은 단 하나. 어릴 적 헤어진 어머니 ‘히노와’를 다시 만나는 것. 하지만 ‘히노와’가 있는 곳은 야왕 ‘호우센’이 군림하는 지상의 법이 통하지 않는 지하도시 요시와라 도원향. ‘세이타’의 간절한 소원을 외면할 수 없었던 ‘긴토키’와 해결사 일행은 요시와라에 발을 들인다. 그 선택은 도시를 뒤흔드는 거대한 충돌로 번지는데…",
    "posterUrl": "https://image.tmdb.org/t/p/w500/mVtUatYLMj30v8Gpv5dYfE2p2XT.jpg"
  },
  {
    "movieCd": "20252402",
    "movieNm": "군체",
    "openDt": "2026-05-21",
    "genreNm": "액션,스릴러,공포,미스터리",
    "nationAlt": "한국",
    "director": "연상호",
    "isReRelease": false,
    "posterUrl": "https://image.tmdb.org/t/p/w500/tzjoWjgro6HllRGei0wb11e6AEt.jpg",
    "overview": "서울 도심의 초고층 빌딩에서 정체불명의 집단 감염사태가 발생한다. 건물은 순식간에 봉쇄되고, 그 안에 있던 사람들은 그대로 고립된다. 처음에는 짐승처럼 기어다니던 감염자들은 점점 진화하며 두 발로 걷기 시작하고, 사람을 식별하며 무리를 지어 생존자들을 공격한다. 생명공학자 권세정과 생존자들은 자신의 몸에 백신을 주입했다고 신고한 서영철을 찾아 구조대가 기다리는 옥상으로 향한다. 하지만 올라갈수록 상황은 점점 더 예측할 수 없게 변해가고, 서영철은 감염자들을 앞세워 생존자들 앞을 막아서는데..."
  },
  {
    "movieCd": "20262168",
    "movieNm": "아이엠 포포",
    "openDt": "2026-05-21",
    "genreNm": "애니메이션,SF,드라마",
    "nationAlt": "한국",
    "director": "Kim Il-dong",
    "isReRelease": false,
    "overview": "1976년, 가정용 컴퓨터로 태어난 '포포'. 위험에 빠진 아기를 구한 순간, 그는 처음으로 존재의 이유를 자각한다. 수십 년 후, 포포는 인간을 수호하는 경찰 시스템으로 진화한다. 그리고 어느 날, 빅데이터가 예측한 미래의 범죄자를 선제적으로 제거한다. 세상은 뒤집혔고, '포포'는 스스로의 선택을 의심하지 않았다. 모든 것은 오직 인간을 위한 최적의 판단이었다고. 치열한 법정 공방 속에서, '포포'는 처음으로 자신의 ‘논리’와 인간의 ‘감정’ 사이 균열을 마주한다. 완벽한 논리로 움직이는 알고리즘과, 비합리적인 감정으로 살아가는 인간. 과연 이 둘은 같은 시대를 함께 살아갈 수 있을까?",
    "posterUrl": "https://image.tmdb.org/t/p/w500/opSju92cW1iM9seqsThT6NMQ6re.jpg"
  },
  {
    "movieCd": "20262941",
    "movieNm": "한복 입은 남자",
    "openDt": "2026-05-21",
    "genreNm": "애니메이션,역사,미스터리",
    "nationAlt": "한국",
    "director": "Lee Sang-hoon",
    "isReRelease": false,
    "overview": "천재 과학자 장영실은 세종의 사랑을 받아서 노비에서 종3품의 벼슬에 오르지만 1442년 가마 사건으로 역사에서 완전히 사라진다. 그는 어디로 사라진 것일까? 20세기 런던, 크리스틴 경 매장에 올라온 루벤스 화가의 <한복 입은 남자>. 루벤스가 그린 알 수 없는 동양인의 정체는 15세기 세종대왕 시절로부터 시작된다. 노비 신분이었지만 머리가 총명했던 장영실은 중국 명나라로부터 죽이거나 명나라로 보내라는 명령을 받게 된다. 세종의 도움으로 명나라의 탐험가인 정화 대장과 함께 유럽으로 떠나 이탈리아 교황을 만나지만 세상이 둥글다고 생각하는 장영실을 이단으로 여겨 죽이라고 한다. 교황으로부터 도망쳐서, 홀로 피렌체에 도망간 장영실은 7살의 어린 레오나르도 다빈치를 만나, 함께 하늘을 나는 기계 '비차'를 연구하게 되는데..",
    "posterUrl": "https://image.tmdb.org/t/p/w500/o4RGQMYv5kSBZod3UAqNU1zqpfP.jpg"
  },
  {
    "movieCd": "20263222",
    "movieNm": "극장판 호빵맨: 세균맨과 그림책의 루룬",
    "openDt": "2026-05-23",
    "genreNm": "애니메이션,판타지,가족",
    "nationAlt": "일본",
    "director": "카와고에 준",
    "isReRelease": false,
    "overview": "어느 날, 세균맨은 한 권의 그림책을 발견한다. 그림책 속에서 “사랑과 용기의 전사 세균맨, 도와줘!!”라는 목소리가 들려오고, 그대로 그림책 속으로 빨려 들어가게 된다. 사막 너머로 펼쳐진 거대한 숲에서 만난 것은 숲의 요정 ‘루룬’. 겁이 많아 용기를 내지 못하는 루룬은, 숲에서 난동을 부리는 ‘휘리릭 코끼리’를 물리쳐 달라고 세균맨에게 부탁한다. 처음에는 내켜 하지 않던 세균맨이지만, 포기하지 않고 맞서 싸우는 그의 모습을 보며 루룬도 점점 용기를 얻게 된다. 하지만 휘리릭 코끼리의 강력한 힘에 큰 위기를 맞이하고, 절체절명의 순간, 세균맨은 루룬에게 “호빵맨을 불러와!”라고 전한다—.",
    "posterUrl": "https://image.tmdb.org/t/p/w500/j8PjZuz2RZTEg07TVm9Ru2o0dGi.jpg"
  },
  {
    "movieCd": "20263363",
    "movieNm": "리마인더스 오브 힘",
    "openDt": "2026-05-27",
    "genreNm": "로맨스,드라마",
    "nationAlt": "미국",
    "director": "바네사 캐스윌",
    "isReRelease": false,
    "overview": "When Diem's custodial grandparents adamantly refuse Kenna's attempts to see her daughter, Kenna discovers unexpected compassion, and then something truer and deeper, with former NFL player and local bar owner Ledger. As their secret romance develops, so do the dangers for both of them, leading Kenna toward heartbreak and, ultimately, the hope for a second chance.",
    "posterUrl": "https://image.tmdb.org/t/p/w500/7L6rceYgzQ0NeHD7PRDNrRoQ291.jpg"
  },
  {
    "movieCd": "20262788",
    "movieNm": "쇼타씨의 마지막 출장",
    "openDt": "2026-05-27",
    "genreNm": "드라마",
    "nationAlt": "한국",
    "director": "이주형",
    "isReRelease": false,
    "overview": "한국으로 마지막 출장을 앞두고 있는 강철맨 CEO 쇼타. 헤어진 연인의 마음을 돌리려고 그녀의 고향 에노시마로 여행 온 한국 청년 대성. 두 사람은 우연히 라멘 가게에서 만나게 되고 쇼타의 사직서와 대성의 편지가 바뀌게 되면서 예상치 못한 인연이 시작된다. 그리고 쇼타와 대성은 상대의 전하지 못했던 마음을 대신 전하며 서로의 삶 속으로 들어가게 되는데…",
    "posterUrl": "https://image.tmdb.org/t/p/w500/oB05aa4yU5yRLMyftbLrphKjd41.jpg"
  },
  {
    "movieCd": "20248252",
    "movieNm": "와일드 씽",
    "openDt": "2026-06-03",
    "genreNm": "코미디,음악",
    "nationAlt": "한국",
    "director": "손재곤",
    "isReRelease": false,
    "overview": "가요계를 휩쓸었지만 예기치 못한 사건에 휘말려 하루아침에 해체된 3인조 혼성 댄스 그룹 '트라이앵글'이 20년 만에 찾아온 재기의 기회를 잡기 위해 무모한 도전을 벌이는 코미디 영화",
    "posterUrl": "https://image.tmdb.org/t/p/w500/vpszanJFXaRNc9iytuZaaK3fcii.jpg"
  }
]